<?xml version="1.0" encoding="utf-8"?>
<TextureAtlas imagePath="the-dark-lord.png">
	<!-- Created with Adobe Animate version 21.0.0.35450 -->
	<!-- http://www.adobe.com/products/animate.html -->
	<SubTexture name="TDL Down0000" x="5" y="5" width="923" height="402"/>
	<SubTexture name="TDL Down0001" x="968" y="5" width="923" height="402"/>
	<SubTexture name="TDL Down0002" x="1931" y="5" width="923" height="402"/>
	<SubTexture name="TDL Down0003" x="2894" y="5" width="923" height="402"/>
	<SubTexture name="TDL Down0004" x="3857" y="5" width="923" height="402"/>
	<SubTexture name="TDL Down0005" x="4820" y="5" width="923" height="402"/>
	<SubTexture name="TDL Down0006" x="5783" y="5" width="923" height="402"/>
	<SubTexture name="TDL Down0007" x="6746" y="5" width="923" height="402"/>
	<SubTexture name="TDL Down0008" x="6746" y="5" width="923" height="402"/>
	<SubTexture name="TDL Down0009" x="6746" y="5" width="923" height="402"/>
	<SubTexture name="TDL Idle0000" x="7709" y="5" width="197" height="560"/>
	<SubTexture name="TDL Idle0001" x="7709" y="5" width="197" height="560"/>
	<SubTexture name="TDL Idle0002" x="7709" y="5" width="197" height="560"/>
	<SubTexture name="TDL Idle0003" x="7946" y="5" width="197" height="560"/>
	<SubTexture name="TDL Idle0004" x="7946" y="5" width="197" height="560"/>
	<SubTexture name="TDL Idle0005" x="5" y="605" width="197" height="560"/>
	<SubTexture name="TDL Idle0006" x="5" y="605" width="197" height="560"/>
	<SubTexture name="TDL Idle0007" x="242" y="605" width="197" height="560"/>
	<SubTexture name="TDL Idle0008" x="242" y="605" width="197" height="560"/>
	<SubTexture name="TDL Idle0009" x="479" y="605" width="197" height="560"/>
	<SubTexture name="TDL Idle0010" x="479" y="605" width="197" height="560"/>
	<SubTexture name="TDL Idle0011" x="716" y="605" width="197" height="560"/>
	<SubTexture name="TDL Idle0012" x="716" y="605" width="197" height="560"/>
	<SubTexture name="TDL Idle0013" x="953" y="605" width="197" height="560"/>
	<SubTexture name="TDL Idle0014" x="953" y="605" width="197" height="560"/>
	<SubTexture name="TDL Idle0015" x="7709" y="5" width="197" height="560"/>
	<SubTexture name="TDL Idle0016" x="7709" y="5" width="197" height="560"/>
	<SubTexture name="TDL Idle0017" x="7709" y="5" width="197" height="560"/>
	<SubTexture name="TDL Idle0018" x="7946" y="5" width="197" height="560"/>
	<SubTexture name="TDL Idle0019" x="7946" y="5" width="197" height="560"/>
	<SubTexture name="TDL Idle0020" x="5" y="605" width="197" height="560"/>
	<SubTexture name="TDL Idle0021" x="5" y="605" width="197" height="560"/>
	<SubTexture name="TDL Idle0022" x="242" y="605" width="197" height="560"/>
	<SubTexture name="TDL Idle0023" x="242" y="605" width="197" height="560"/>
	<SubTexture name="TDL Idle0024" x="479" y="605" width="197" height="560"/>
	<SubTexture name="TDL Idle0025" x="479" y="605" width="197" height="560"/>
	<SubTexture name="TDL Idle0026" x="716" y="605" width="197" height="560"/>
	<SubTexture name="TDL Idle0027" x="716" y="605" width="197" height="560"/>
	<SubTexture name="TDL Idle0028" x="953" y="605" width="197" height="560"/>
	<SubTexture name="TDL Idle0029" x="953" y="605" width="197" height="560"/>
	<SubTexture name="TDL Left0000" x="1190" y="605" width="524" height="544"/>
	<SubTexture name="TDL Left0001" x="1754" y="605" width="524" height="544"/>
	<SubTexture name="TDL Left0002" x="2318" y="605" width="524" height="544"/>
	<SubTexture name="TDL Left0003" x="2882" y="605" width="524" height="544"/>
	<SubTexture name="TDL Left0004" x="3446" y="605" width="524" height="544"/>
	<SubTexture name="TDL Left0005" x="4010" y="605" width="524" height="544"/>
	<SubTexture name="TDL Left0006" x="4574" y="605" width="524" height="544"/>
	<SubTexture name="TDL Left0007" x="5138" y="605" width="524" height="544"/>
	<SubTexture name="TDL Left0008" x="5702" y="605" width="524" height="544"/>
	<SubTexture name="TDL Left0009" x="6266" y="605" width="524" height="544"/>
	<SubTexture name="TDL Right0000" x="6830" y="605" width="1073" height="535"/>
	<SubTexture name="TDL Right0001" x="5" y="1205" width="1073" height="535"/>
	<SubTexture name="TDL Right0002" x="1118" y="1205" width="1073" height="535"/>
	<SubTexture name="TDL Right0003" x="2231" y="1205" width="1073" height="535"/>
	<SubTexture name="TDL Right0004" x="3344" y="1205" width="1073" height="535"/>
	<SubTexture name="TDL Right0005" x="4457" y="1205" width="1073" height="535"/>
	<SubTexture name="TDL Right0006" x="5570" y="1205" width="1073" height="535"/>
	<SubTexture name="TDL Right0007" x="6683" y="1205" width="1073" height="535"/>
	<SubTexture name="TDL Right0008" x="5" y="1780" width="1073" height="535"/>
	<SubTexture name="TDL Right0009" x="1118" y="1780" width="1073" height="535"/>
	<SubTexture name="TDL Slice0000" x="2231" y="1780" width="1058" height="759"/>
	<SubTexture name="TDL Slice0001" x="3329" y="1780" width="1058" height="759"/>
	<SubTexture name="TDL Slice0002" x="4427" y="1780" width="1058" height="759"/>
	<SubTexture name="TDL Slice0003" x="5525" y="1780" width="1058" height="759"/>
	<SubTexture name="TDL Slice0004" x="6623" y="1780" width="1058" height="759"/>
	<SubTexture name="TDL Slice0005" x="5" y="2579" width="1058" height="759"/>
	<SubTexture name="TDL Slice0006" x="1103" y="2579" width="1058" height="759"/>
	<SubTexture name="TDL Slice0007" x="2201" y="2579" width="1058" height="759"/>
	<SubTexture name="TDL Slice0008" x="3299" y="2579" width="1058" height="759"/>
	<SubTexture name="TDL Slice0009" x="4397" y="2579" width="1058" height="759"/>
	<SubTexture name="TDL Slice0010" x="5495" y="2579" width="1058" height="759"/>
	<SubTexture name="TDL Slice0011" x="6593" y="2579" width="1058" height="759"/>
	<SubTexture name="TDL Slice0012" x="5" y="3378" width="1058" height="759"/>
	<SubTexture name="TDL Slice0013" x="1103" y="3378" width="1058" height="759"/>
	<SubTexture name="TDL Slice0014" x="2201" y="3378" width="1058" height="759"/>
	<SubTexture name="TDL Slice0015" x="3299" y="3378" width="1058" height="759"/>
	<SubTexture name="TDL Slice0016" x="4397" y="3378" width="1058" height="759"/>
	<SubTexture name="TDL Slice0017" x="5495" y="3378" width="1058" height="759"/>
	<SubTexture name="TDL Slice0018" x="6593" y="3378" width="1058" height="759"/>
	<SubTexture name="TDL Slice0019" x="5" y="4177" width="1058" height="759"/>
	<SubTexture name="TDL Slice0020" x="1103" y="4177" width="1058" height="759"/>
	<SubTexture name="TDL Slice0021" x="5495" y="2579" width="1058" height="759"/>
	<SubTexture name="TDL Slice0022" x="6593" y="2579" width="1058" height="759"/>
	<SubTexture name="TDL Slice0023" x="5" y="3378" width="1058" height="759"/>
	<SubTexture name="TDL Up0000" x="2201" y="4177" width="551" height="726"/>
	<SubTexture name="TDL Up0001" x="2792" y="4177" width="551" height="726"/>
	<SubTexture name="TDL Up0002" x="3383" y="4177" width="551" height="726"/>
	<SubTexture name="TDL Up0003" x="3974" y="4177" width="551" height="726"/>
	<SubTexture name="TDL Up0004" x="4565" y="4177" width="551" height="726"/>
	<SubTexture name="TDL Up0005" x="5156" y="4177" width="551" height="726"/>
	<SubTexture name="TDL Up0006" x="5156" y="4177" width="551" height="726"/>
	<SubTexture name="TDL Up0007" x="5156" y="4177" width="551" height="726"/>
	<SubTexture name="TDL Up0008" x="5156" y="4177" width="551" height="726"/>
	<SubTexture name="TDL Up0009" x="5156" y="4177" width="551" height="726"/>
</TextureAtlas>
