{
	"song": {
		"player1": "animator-bf",
		"sectionLengths": [],
		"player2": "StickFigureRed",
		"notes": [
			{
				"typeOfSection": 0,
				"lengthInSteps": 16,
				"sectionNotes": [],
				"mustHitSection": false
			},
			{
				"typeOfSection": 0,
				"lengthInSteps": 16,
				"sectionNotes": [],
				"mustHitSection": false
			},
			{
				"typeOfSection": 0,
				"lengthInSteps": 16,
				"sectionNotes": [],
				"mustHitSection": true
			},
			{
				"typeOfSection": 0,
				"lengthInSteps": 16,
				"sectionNotes": [],
				"mustHitSection": true
			},
			{
				"typeOfSection": 0,
				"lengthInSteps": 16,
				"sectionNotes": [
					[
						5230.76923076923,
						3,
						0
					],
					[
						5384.61538461538,
						2,
						0
					],
					[
						4923.07692307692,
						0,
						230.769230769231
					],
					[
						4923.07692307692,
						2,
						0
					],
					[
						5384.61538461538,
						1,
						0
					],
					[
						5846.15384615384,
						3,
						0
					],
					[
						6000,
						0,
						0
					],
					[
						5692.30769230769,
						1,
						0
					]
				],
				"mustHitSection": false
			},
			{
				"typeOfSection": 0,
				"lengthInSteps": 16,
				"sectionNotes": [
					[
						6153.84615384615,
						2,
						230.769230769231
					],
					[
						6153.84615384615,
						3,
						0
					],
					[
						6461.53846153846,
						0,
						0
					],
					[
						6615.38461538461,
						2,
						0
					],
					[
						6769.23076923077,
						1,
						0
					],
					[
						6769.23076923077,
						3,
						0
					],
					[
						6923.07692307692,
						0,
						0
					],
					[
						7076.92307692308,
						2,
						230.769230769231
					]
				],
				"mustHitSection": false
			},
			{
				"typeOfSection": 0,
				"lengthInSteps": 16,
				"sectionNotes": [
					[
						7692.30769230769,
						3,
						0
					],
					[
						7846.15384615385,
						2,
						0
					],
					[
						7384.61538461538,
						0,
						230.769230769231
					],
					[
						7384.61538461538,
						2,
						0
					],
					[
						7846.15384615385,
						1,
						0
					],
					[
						8307.69230769231,
						3,
						0
					],
					[
						8461.53846153846,
						0,
						0
					],
					[
						8153.84615384615,
						1,
						0
					]
				],
				"mustHitSection": true
			},
			{
				"typeOfSection": 0,
				"lengthInSteps": 16,
				"sectionNotes": [
					[
						8615.38461538462,
						2,
						230.769230769231
					],
					[
						8615.38461538462,
						3,
						0
					],
					[
						8923.07692307692,
						0,
						0
					],
					[
						9076.92307692308,
						2,
						0
					],
					[
						9230.76923076923,
						1,
						0
					],
					[
						9230.76923076923,
						3,
						0
					],
					[
						9384.61538461538,
						0,
						0
					],
					[
						9538.46153846154,
						2,
						230.769230769231
					]
				],
				"mustHitSection": true
			},
			{
				"typeOfSection": 0,
				"lengthInSteps": 16,
				"sectionNotes": [
					[
						9846.15384615384,
						2,
						230.769230769231
					],
					[
						10153.8461538462,
						0,
						0
					],
					[
						10307.6923076923,
						1,
						0
					],
					[
						10307.6923076923,
						3,
						0
					],
					[
						10615.3846153846,
						0,
						230.769230769231
					],
					[
						10923.0769230769,
						1,
						0
					]
				],
				"mustHitSection": false
			},
			{
				"typeOfSection": 0,
				"lengthInSteps": 16,
				"sectionNotes": [
					[
						11076.9230769231,
						2,
						0
					],
					[
						11230.7692307692,
						3,
						0
					],
					[
						11384.6153846154,
						2,
						0
					],
					[
						11538.4615384615,
						1,
						0
					],
					[
						11692.3076923077,
						0,
						230.769230769231
					],
					[
						11692.3076923077,
						1,
						0
					],
					[
						12000,
						3,
						230.769230769231
					],
					[
						11230.7692307692,
						0,
						0
					]
				],
				"mustHitSection": false
			},
			{
				"typeOfSection": 0,
				"lengthInSteps": 16,
				"sectionNotes": [
					[
						12307.6923076923,
						2,
						230.769230769231
					],
					[
						12615.3846153846,
						0,
						0
					],
					[
						12769.2307692308,
						1,
						0
					],
					[
						12769.2307692308,
						3,
						0
					],
					[
						13076.9230769231,
						0,
						230.769230769231
					],
					[
						13384.6153846154,
						1,
						0
					],
					[
						12307.6923076923,
						6,
						307.692307692308
					]
				],
				"mustHitSection": true
			},
			{
				"typeOfSection": 0,
				"lengthInSteps": 16,
				"sectionNotes": [
					[
						13538.4615384615,
						2,
						0
					],
					[
						13692.3076923077,
						3,
						0
					],
					[
						13846.1538461538,
						2,
						0
					],
					[
						14000,
						1,
						0
					],
					[
						14153.8461538462,
						0,
						230.769230769231
					],
					[
						14153.8461538462,
						1,
						0
					],
					[
						14461.5384615385,
						3,
						230.769230769231
					],
					[
						13692.3076923077,
						0,
						0
					]
				],
				"mustHitSection": true
			},
			{
				"typeOfSection": 0,
				"lengthInSteps": 16,
				"sectionNotes": [
					[
						14769.2307692308,
						6,
						307.692307692308
					],
					[
						14769.2307692308,
						2,
						0
					],
					[
						14769.2307692308,
						3,
						0
					],
					[
						15076.9230769231,
						1,
						0
					],
					[
						15076.9230769231,
						0,
						0
					],
					[
						15384.6153846154,
						0,
						0
					],
					[
						15384.6153846154,
						3,
						0
					],
					[
						15461.5384615385,
						2,
						0
					],
					[
						15538.4615384615,
						0,
						0
					],
					[
						15615.3846153846,
						1,
						0
					],
					[
						15692.3076923077,
						0,
						0
					],
					[
						15846.1538461538,
						1,
						0
					]
				],
				"mustHitSection": false
			},
			{
				"typeOfSection": 0,
				"lengthInSteps": 16,
				"sectionNotes": [
					[
						16000,
						2,
						230.769230769231
					],
					[
						16000,
						3,
						0
					],
					[
						16307.6923076923,
						0,
						76.9230769230769
					],
					[
						16461.5384615385,
						3,
						76.9230769230769
					],
					[
						16615.3846153846,
						1,
						230.769230769231
					],
					[
						16615.3846153846,
						2,
						0
					],
					[
						16923.0769230769,
						0,
						230.769230769231
					]
				],
				"mustHitSection": false
			},
			{
				"typeOfSection": 0,
				"lengthInSteps": 16,
				"sectionNotes": [
					[
						17230.7692307692,
						0,
						0
					],
					[
						17538.4615384615,
						3,
						0
					],
					[
						17230.7692307692,
						1,
						0
					],
					[
						17538.4615384615,
						2,
						0
					],
					[
						17846.1538461538,
						1,
						0
					],
					[
						17846.1538461538,
						2,
						0
					],
					[
						17923.0769230769,
						3,
						0
					],
					[
						18000,
						0,
						0
					],
					[
						18076.9230769231,
						2,
						0
					],
					[
						18153.8461538462,
						3,
						0
					],
					[
						18307.6923076923,
						0,
						0
					],
					[
						17230.7692307692,
						6,
						307.692307692308
					]
				],
				"mustHitSection": true
			},
			{
				"typeOfSection": 0,
				"lengthInSteps": 16,
				"sectionNotes": [
					[
						18461.5384615385,
						2,
						230.769230769231
					],
					[
						19076.9230769231,
						0,
						230.769230769231
					],
					[
						19076.9230769231,
						1,
						230.769230769231
					],
					[
						18923.0769230769,
						3,
						76.9230769230769
					],
					[
						18769.2307692308,
						1,
						76.9230769230769
					],
					[
						19384.6153846154,
						3,
						230.769230769231
					]
				],
				"mustHitSection": true
			},
			{
				"typeOfSection": 0,
				"lengthInSteps": 16,
				"sectionNotes": [
					[
						19692.3076923077,
						6,
						307.692307692308
					],
					[
						19692.3076923077,
						2,
						230.769230769231
					],
					[
						20000,
						0,
						0
					],
					[
						20153.8461538461,
						3,
						0
					],
					[
						20307.6923076923,
						0,
						230.769230769231
					],
					[
						20307.6923076923,
						1,
						76.9230769230769
					],
					[
						20615.3846153846,
						2,
						0
					],
					[
						20615.3846153846,
						3,
						0
					],
					[
						20769.2307692308,
						1,
						0
					]
				],
				"mustHitSection": false
			},
			{
				"typeOfSection": 0,
				"lengthInSteps": 16,
				"sectionNotes": [
					[
						20923.0769230769,
						0,
						0
					],
					[
						21076.9230769231,
						2,
						0
					],
					[
						21230.7692307692,
						0,
						0
					],
					[
						21384.6153846154,
						1,
						0
					],
					[
						21230.7692307692,
						3,
						76.9230769230769
					],
					[
						21538.4615384615,
						0,
						230.769230769231
					],
					[
						21846.1538461538,
						1,
						230.769230769231
					],
					[
						21846.1538461538,
						2,
						0
					]
				],
				"mustHitSection": false
			},
			{
				"typeOfSection": 0,
				"lengthInSteps": 16,
				"sectionNotes": [
					[
						22153.8461538461,
						0,
						0
					],
					[
						22307.6923076923,
						1,
						0
					],
					[
						22461.5384615385,
						0,
						0
					],
					[
						22461.5384615385,
						3,
						0
					],
					[
						22615.3846153846,
						2,
						0
					],
					[
						22769.2307692308,
						1,
						0
					],
					[
						23230.7692307692,
						1,
						0
					],
					[
						22923.0769230769,
						0,
						230.769230769231
					],
					[
						22923.0769230769,
						2,
						0
					]
				],
				"mustHitSection": false
			},
			{
				"typeOfSection": 0,
				"lengthInSteps": 16,
				"sectionNotes": [
					[
						23384.6153846154,
						2,
						230.769230769231
					],
					[
						23692.3076923077,
						1,
						0
					],
					[
						23692.3076923077,
						0,
						0
					],
					[
						23846.1538461538,
						3,
						0
					],
					[
						24000,
						0,
						0
					],
					[
						24307.6923076923,
						1,
						230.769230769231
					],
					[
						24153.8461538462,
						2,
						0
					]
				],
				"mustHitSection": false
			},
			{
				"typeOfSection": 0,
				"lengthInSteps": 16,
				"sectionNotes": [
					[
						24615.3846153846,
						2,
						230.769230769231
					],
					[
						24923.0769230769,
						0,
						0
					],
					[
						25076.9230769231,
						3,
						0
					],
					[
						25230.7692307692,
						0,
						230.769230769231
					],
					[
						25230.7692307692,
						1,
						76.9230769230769
					],
					[
						25538.4615384615,
						2,
						0
					],
					[
						25538.4615384615,
						3,
						0
					],
					[
						25692.3076923077,
						1,
						0
					]
				],
				"mustHitSection": true
			},
			{
				"typeOfSection": 0,
				"lengthInSteps": 16,
				"sectionNotes": [
					[
						25846.1538461538,
						0,
						0
					],
					[
						26000,
						2,
						0
					],
					[
						26153.8461538462,
						0,
						0
					],
					[
						26307.6923076923,
						1,
						0
					],
					[
						26153.8461538462,
						3,
						76.9230769230769
					],
					[
						26461.5384615385,
						0,
						230.769230769231
					],
					[
						26769.2307692308,
						1,
						230.769230769231
					],
					[
						26769.2307692308,
						2,
						0
					]
				],
				"mustHitSection": true
			},
			{
				"typeOfSection": 0,
				"lengthInSteps": 16,
				"sectionNotes": [
					[
						27076.9230769231,
						0,
						0
					],
					[
						27230.7692307692,
						1,
						0
					],
					[
						27384.6153846154,
						0,
						0
					],
					[
						27384.6153846154,
						3,
						0
					],
					[
						27538.4615384615,
						2,
						0
					],
					[
						27692.3076923077,
						1,
						0
					],
					[
						28153.8461538462,
						1,
						0
					],
					[
						27846.1538461538,
						0,
						230.769230769231
					],
					[
						27846.1538461538,
						2,
						0
					]
				],
				"mustHitSection": true
			},
			{
				"typeOfSection": 0,
				"lengthInSteps": 16,
				"sectionNotes": [
					[
						28307.6923076923,
						2,
						230.769230769231
					],
					[
						28615.3846153846,
						1,
						0
					],
					[
						28615.3846153846,
						0,
						0
					],
					[
						28769.2307692308,
						3,
						0
					],
					[
						28923.0769230769,
						0,
						0
					],
					[
						29230.7692307692,
						1,
						230.769230769231
					],
					[
						29076.9230769231,
						2,
						0
					]
				],
				"mustHitSection": true
			},
			{
				"typeOfSection": 0,
				"lengthInSteps": 16,
				"sectionNotes": [
					[
						29538.4615384615,
						4,
						538.461538461538
					],
					[
						29538.4615384615,
						7,
						0
					],
					[
						30153.8461538462,
						5,
						538.461538461538
					],
					[
						30153.8461538462,
						6,
						0
					],
					[
						29538.4615384615,
						2,
						0
					],
					[
						29692.3076923077,
						0,
						0
					],
					[
						29846.1538461538,
						3,
						0
					],
					[
						29846.1538461538,
						1,
						230.769230769231
					],
					[
						30153.8461538462,
						0,
						0
					],
					[
						30307.6923076923,
						3,
						0
					],
					[
						30461.5384615385,
						0,
						0
					],
					[
						30461.5384615385,
						2,
						0
					],
					[
						30615.3846153846,
						1,
						0
					]
				],
				"mustHitSection": false
			},
			{
				"typeOfSection": 0,
				"lengthInSteps": 16,
				"sectionNotes": [
					[
						30769.2307692308,
						6,
						538.461538461538
					],
					[
						30769.2307692308,
						7,
						0
					],
					[
						31384.6153846154,
						4,
						230.769230769231
					],
					[
						31692.3076923077,
						7,
						230.769230769231
					],
					[
						31692.3076923077,
						5,
						0
					],
					[
						30769.2307692308,
						0,
						230.769230769231
					],
					[
						31076.9230769231,
						2,
						0
					],
					[
						31076.9230769231,
						3,
						0
					],
					[
						31230.7692307692,
						1,
						0
					],
					[
						31384.6153846154,
						2,
						230.769230769231
					],
					[
						31692.3076923077,
						0,
						0
					],
					[
						31692.3076923077,
						3,
						0
					],
					[
						31846.1538461539,
						1,
						0
					]
				],
				"mustHitSection": false
			},
			{
				"typeOfSection": 0,
				"lengthInSteps": 16,
				"sectionNotes": [
					[
						32000,
						6,
						230.769230769231
					],
					[
						32307.6923076923,
						7,
						230.769230769231
					],
					[
						32307.6923076923,
						4,
						0
					],
					[
						32615.3846153846,
						5,
						230.769230769231
					],
					[
						32923.0769230769,
						4,
						0
					],
					[
						32923.0769230769,
						6,
						230.769230769231
					],
					[
						32000,
						0,
						230.769230769231
					],
					[
						32000,
						2,
						230.769230769231
					],
					[
						32307.6923076923,
						1,
						230.769230769231
					],
					[
						32307.6923076923,
						3,
						230.769230769231
					],
					[
						32615.3846153846,
						2,
						0
					],
					[
						32769.2307692308,
						0,
						0
					],
					[
						32923.0769230769,
						2,
						230.769230769231
					]
				],
				"mustHitSection": false
			},
			{
				"typeOfSection": 0,
				"lengthInSteps": 16,
				"sectionNotes": [
					[
						33230.7692307692,
						5,
						538.461538461538
					],
					[
						34153.8461538461,
						4,
						230.769230769231
					],
					[
						33846.1538461538,
						7,
						230.769230769231
					],
					[
						33846.1538461538,
						6,
						0
					],
					[
						34153.8461538461,
						5,
						0
					],
					[
						33230.7692307692,
						1,
						230.769230769231
					],
					[
						33538.4615384615,
						0,
						0
					],
					[
						33538.4615384615,
						3,
						0
					],
					[
						33692.3076923077,
						2,
						0
					],
					[
						33846.1538461539,
						0,
						538.461538461538
					]
				],
				"mustHitSection": false
			},
			{
				"typeOfSection": 0,
				"lengthInSteps": 16,
				"sectionNotes": [
					[
						34461.5384615385,
						4,
						538.461538461538
					],
					[
						34461.5384615385,
						7,
						0
					],
					[
						35076.9230769231,
						5,
						538.461538461538
					],
					[
						35076.9230769231,
						6,
						0
					],
					[
						34461.5384615385,
						2,
						0
					],
					[
						34615.3846153846,
						0,
						0
					],
					[
						34769.2307692308,
						3,
						0
					],
					[
						34769.2307692308,
						1,
						230.769230769231
					],
					[
						35076.9230769231,
						0,
						0
					],
					[
						35230.7692307692,
						3,
						0
					],
					[
						35384.6153846154,
						0,
						0
					],
					[
						35384.6153846154,
						2,
						0
					],
					[
						35538.4615384615,
						1,
						0
					]
				],
				"mustHitSection": true
			},
			{
				"typeOfSection": 0,
				"lengthInSteps": 16,
				"sectionNotes": [
					[
						35692.3076923077,
						6,
						538.461538461538
					],
					[
						35692.3076923077,
						7,
						0
					],
					[
						36307.6923076923,
						4,
						230.769230769231
					],
					[
						36615.3846153846,
						7,
						230.769230769231
					],
					[
						36615.3846153846,
						5,
						0
					],
					[
						35692.3076923077,
						0,
						230.769230769231
					],
					[
						36000,
						2,
						0
					],
					[
						36000,
						3,
						0
					],
					[
						36153.8461538462,
						1,
						0
					],
					[
						36307.6923076923,
						2,
						230.769230769231
					],
					[
						36615.3846153846,
						0,
						0
					],
					[
						36615.3846153846,
						3,
						0
					],
					[
						36769.2307692308,
						1,
						0
					]
				],
				"mustHitSection": true
			},
			{
				"typeOfSection": 0,
				"lengthInSteps": 16,
				"sectionNotes": [
					[
						36923.0769230769,
						6,
						230.769230769231
					],
					[
						37230.7692307692,
						7,
						230.769230769231
					],
					[
						37230.7692307692,
						4,
						0
					],
					[
						37538.4615384615,
						5,
						230.769230769231
					],
					[
						37846.1538461538,
						4,
						0
					],
					[
						37846.1538461538,
						6,
						230.769230769231
					],
					[
						36923.0769230769,
						0,
						230.769230769231
					],
					[
						36923.0769230769,
						2,
						230.769230769231
					],
					[
						37230.7692307692,
						1,
						230.769230769231
					],
					[
						37230.7692307692,
						3,
						230.769230769231
					],
					[
						37538.4615384615,
						2,
						0
					],
					[
						37692.3076923077,
						0,
						0
					],
					[
						37846.1538461539,
						2,
						230.769230769231
					]
				],
				"mustHitSection": true
			},
			{
				"typeOfSection": 0,
				"lengthInSteps": 16,
				"sectionNotes": [
					[
						38153.8461538461,
						5,
						538.461538461538
					],
					[
						38769.2307692308,
						6,
						0
					],
					[
						38153.8461538462,
						1,
						230.769230769231
					],
					[
						38461.5384615385,
						0,
						0
					],
					[
						38461.5384615385,
						3,
						0
					],
					[
						38615.3846153846,
						2,
						0
					],
					[
						38769.2307692308,
						0,
						538.461538461538
					],
					[
						38769.2307692308,
						7,
						538.461538461538
					]
				],
				"mustHitSection": true
			},
			{
				"typeOfSection": 0,
				"lengthInSteps": 16,
				"sectionNotes": [
					[
						39384.6153846154,
						1,
						0
					],
					[
						39384.6153846154,
						2,
						0
					],
					[
						39692.3076923077,
						2,
						0
					],
					[
						39692.3076923077,
						1,
						0
					],
					[
						40000,
						3,
						0
					],
					[
						40000,
						1,
						0
					],
					[
						40153.8461538462,
						0,
						0
					],
					[
						40461.5384615385,
						2,
						0
					]
				],
				"mustHitSection": false
			},
			{
				"typeOfSection": 0,
				"lengthInSteps": 16,
				"sectionNotes": [
					[
						40615.3846153846,
						1,
						230.769230769231
					],
					[
						40923.076923077,
						3,
						230.769230769231
					],
					[
						40923.076923077,
						0,
						0
					],
					[
						41230.7692307693,
						2,
						0
					],
					[
						41230.7692307693,
						1,
						0
					],
					[
						41307.6923076923,
						0,
						0
					],
					[
						41384.6153846154,
						1,
						0
					],
					[
						41461.5384615385,
						2,
						0
					],
					[
						41538.4615384616,
						3,
						0
					],
					[
						41692.3076923077,
						1,
						0
					],
					[
						41538.4615384616,
						0,
						0
					]
				],
				"mustHitSection": false
			},
			{
				"typeOfSection": 0,
				"lengthInSteps": 16,
				"sectionNotes": [
					[
						41846.1538461539,
						0,
						230.769230769231
					],
					[
						41846.1538461539,
						2,
						0
					],
					[
						42153.8461538462,
						1,
						0
					],
					[
						42153.8461538462,
						3,
						230.769230769231
					],
					[
						42461.5384615385,
						2,
						0
					],
					[
						42461.5384615385,
						1,
						0
					],
					[
						42615.3846153846,
						0,
						0
					],
					[
						42769.2307692308,
						2,
						0
					],
					[
						42923.076923077,
						1,
						0
					]
				],
				"mustHitSection": false
			},
			{
				"typeOfSection": 0,
				"lengthInSteps": 16,
				"sectionNotes": [
					[
						43076.9230769231,
						3,
						0
					],
					[
						43115.3846153847,
						2,
						0
					],
					[
						43692.3076923077,
						2,
						538.461538461538
					],
					[
						43384.6153846154,
						1,
						0
					]
				],
				"mustHitSection": false
			},
			{
				"typeOfSection": 0,
				"lengthInSteps": 16,
				"sectionNotes": [
					[
						44307.6923076923,
						2,
						0
					],
					[
						44307.6923076923,
						1,
						0
					],
					[
						44615.3846153846,
						1,
						0
					],
					[
						44615.3846153846,
						2,
						0
					],
					[
						44923.076923077,
						0,
						0
					],
					[
						44923.076923077,
						2,
						0
					],
					[
						45076.9230769231,
						3,
						0
					],
					[
						45384.6153846154,
						1,
						0
					]
				],
				"mustHitSection": true
			},
			{
				"typeOfSection": 0,
				"lengthInSteps": 16,
				"sectionNotes": [
					[
						45538.4615384616,
						2,
						230.769230769231
					],
					[
						45846.1538461539,
						0,
						230.769230769231
					],
					[
						45846.1538461539,
						3,
						0
					],
					[
						46153.8461538462,
						1,
						0
					],
					[
						46153.8461538462,
						2,
						0
					],
					[
						46230.7692307693,
						3,
						0
					],
					[
						46307.6923076923,
						2,
						0
					],
					[
						46384.6153846154,
						1,
						0
					],
					[
						46461.5384615385,
						0,
						0
					],
					[
						46615.3846153846,
						2,
						0
					],
					[
						46461.5384615385,
						3,
						0
					]
				],
				"mustHitSection": true
			},
			{
				"typeOfSection": 0,
				"lengthInSteps": 16,
				"sectionNotes": [
					[
						46769.2307692308,
						3,
						230.769230769231
					],
					[
						46769.2307692308,
						1,
						0
					],
					[
						47076.9230769231,
						2,
						0
					],
					[
						47076.9230769231,
						0,
						230.769230769231
					],
					[
						47384.6153846154,
						1,
						0
					],
					[
						47384.6153846154,
						2,
						0
					],
					[
						47538.4615384616,
						3,
						0
					],
					[
						47692.3076923077,
						1,
						0
					],
					[
						47846.1538461539,
						2,
						0
					]
				],
				"mustHitSection": true
			},
			{
				"typeOfSection": 0,
				"lengthInSteps": 16,
				"sectionNotes": [
					[
						48000,
						0,
						0
					],
					[
						48038.4615384616,
						1,
						0
					],
					[
						48615.3846153847,
						1,
						538.461538461538
					],
					[
						48307.6923076923,
						2,
						0
					]
				],
				"mustHitSection": true
			},
			{
				"typeOfSection": 0,
				"lengthInSteps": 16,
				"sectionNotes": [
					[
						49538.4615384616,
						4,
						0
					],
					[
						49692.3076923077,
						6,
						0
					],
					[
						49846.1538461539,
						5,
						230.769230769231
					],
					[
						49846.1538461539,
						7,
						0
					],
					[
						50153.8461538462,
						4,
						0
					],
					[
						50307.6923076923,
						6,
						0
					],
					[
						49230.7692307693,
						6,
						230.769230769231
					],
					[
						49230.7692307693,
						7,
						230.769230769231
					],
					[
						49538.4615384616,
						0,
						0
					],
					[
						49692.3076923077,
						2,
						0
					],
					[
						49846.1538461539,
						1,
						230.769230769231
					],
					[
						49846.1538461539,
						3,
						0
					],
					[
						50153.8461538462,
						0,
						0
					],
					[
						50307.6923076923,
						2,
						0
					],
					[
						49230.7692307693,
						2,
						230.769230769231
					],
					[
						49230.7692307693,
						3,
						230.769230769231
					]
				],
				"mustHitSection": false
			},
			{
				"typeOfSection": 0,
				"lengthInSteps": 16,
				"sectionNotes": [
					[
						50461.5384615385,
						1,
						230.769230769231
					],
					[
						50769.2307692308,
						0,
						0
					],
					[
						50769.2307692308,
						3,
						0
					],
					[
						50923.076923077,
						1,
						0
					],
					[
						51076.9230769231,
						0,
						0
					],
					[
						51076.9230769231,
						2,
						538.461538461538
					],
					[
						50461.5384615385,
						5,
						230.769230769231
					],
					[
						50769.2307692308,
						4,
						0
					],
					[
						50769.2307692308,
						7,
						0
					],
					[
						50923.076923077,
						5,
						0
					],
					[
						51076.9230769231,
						4,
						0
					],
					[
						51076.9230769231,
						6,
						538.461538461538
					]
				],
				"mustHitSection": false
			},
			{
				"typeOfSection": 0,
				"lengthInSteps": 16,
				"sectionNotes": [
					[
						51692.3076923077,
						4,
						230.769230769231
					],
					[
						51692.3076923077,
						7,
						0
					],
					[
						52000,
						5,
						0
					],
					[
						52153.8461538462,
						6,
						0
					],
					[
						52307.6923076924,
						4,
						230.769230769231
					],
					[
						52615.3846153847,
						7,
						0
					],
					[
						52769.2307692308,
						5,
						0
					],
					[
						52307.6923076924,
						7,
						0
					],
					[
						51692.3076923077,
						0,
						230.769230769231
					],
					[
						51692.3076923077,
						3,
						0
					],
					[
						52000,
						1,
						0
					],
					[
						52153.8461538462,
						2,
						0
					],
					[
						52307.6923076924,
						0,
						230.769230769231
					],
					[
						52615.3846153847,
						3,
						0
					],
					[
						52769.2307692308,
						1,
						0
					],
					[
						52307.6923076924,
						3,
						0
					]
				],
				"mustHitSection": true
			},
			{
				"typeOfSection": 0,
				"lengthInSteps": 16,
				"sectionNotes": [
					[
						52923.076923077,
						3,
						384.615384615385
					],
					[
						53384.6153846154,
						2,
						384.615384615385
					],
					[
						53846.1538461539,
						0,
						230.769230769231
					],
					[
						53384.6153846154,
						1,
						384.615384615385
					],
					[
						53846.1538461539,
						3,
						230.769230769231
					],
					[
						52923.076923077,
						7,
						384.615384615385
					],
					[
						53384.6153846154,
						6,
						384.615384615385
					],
					[
						53846.1538461539,
						4,
						230.769230769231
					],
					[
						53384.6153846154,
						5,
						384.615384615385
					],
					[
						53846.1538461539,
						7,
						230.769230769231
					]
				],
				"mustHitSection": true
			},
			{
				"typeOfSection": 0,
				"lengthInSteps": 16,
				"sectionNotes": [
					[
						54153.8461538462,
						4,
						0
					],
					[
						54153.8461538462,
						7,
						0
					],
					[
						54307.6923076924,
						6,
						0
					],
					[
						54461.5384615385,
						7,
						230.769230769231
					],
					[
						54769.2307692308,
						5,
						0
					],
					[
						54769.2307692308,
						4,
						230.769230769231
					],
					[
						55076.9230769231,
						6,
						230.769230769231
					],
					[
						54153.8461538462,
						0,
						0
					],
					[
						54153.8461538462,
						3,
						0
					],
					[
						54307.6923076924,
						2,
						0
					],
					[
						54461.5384615385,
						3,
						230.769230769231
					],
					[
						54769.2307692308,
						1,
						0
					],
					[
						54769.2307692308,
						0,
						230.769230769231
					],
					[
						55076.9230769231,
						2,
						230.769230769231
					]
				],
				"mustHitSection": false
			},
			{
				"typeOfSection": 0,
				"lengthInSteps": 16,
				"sectionNotes": [
					[
						55384.6153846154,
						3,
						0
					],
					[
						55538.4615384616,
						0,
						0
					],
					[
						55692.3076923077,
						2,
						230.769230769231
					],
					[
						56000.0000000001,
						3,
						230.769230769231
					],
					[
						56000.0000000001,
						0,
						0
					],
					[
						55692.3076923077,
						1,
						0
					],
					[
						56307.6923076924,
						0,
						0
					],
					[
						56461.5384615385,
						1,
						0
					],
					[
						55384.6153846154,
						7,
						0
					],
					[
						55538.4615384616,
						4,
						0
					],
					[
						55692.3076923077,
						6,
						230.769230769231
					],
					[
						56000.0000000001,
						7,
						230.769230769231
					],
					[
						56000.0000000001,
						4,
						0
					],
					[
						55692.3076923077,
						5,
						0
					],
					[
						56307.6923076924,
						4,
						0
					],
					[
						56461.5384615385,
						5,
						0
					]
				],
				"mustHitSection": true
			},
			{
				"typeOfSection": 0,
				"lengthInSteps": 16,
				"sectionNotes": [
					[
						56615.3846153847,
						6,
						230.769230769231
					],
					[
						56923.076923077,
						4,
						230.769230769231
					],
					[
						57230.7692307693,
						5,
						230.769230769231
					],
					[
						56923.076923077,
						7,
						0
					],
					[
						57538.4615384616,
						6,
						0
					],
					[
						57692.3076923078,
						7,
						0
					],
					[
						56615.3846153847,
						2,
						230.769230769231
					],
					[
						56923.076923077,
						0,
						230.769230769231
					],
					[
						57230.7692307693,
						1,
						230.769230769231
					],
					[
						56923.076923077,
						3,
						0
					],
					[
						57538.4615384616,
						2,
						0
					],
					[
						57692.3076923078,
						3,
						0
					]
				],
				"mustHitSection": false
			},
			{
				"typeOfSection": 0,
				"lengthInSteps": 16,
				"sectionNotes": [
					[
						57846.1538461539,
						0,
						538.461538461538
					],
					[
						58461.5384615385,
						2,
						538.461538461538
					],
					[
						58461.5384615385,
						3,
						0
					],
					[
						57846.1538461539,
						4,
						538.461538461538
					],
					[
						58461.5384615385,
						6,
						538.461538461538
					],
					[
						58461.5384615385,
						7,
						0
					]
				],
				"mustHitSection": true
			},
			{
				"typeOfSection": 0,
				"lengthInSteps": 16,
				"sectionNotes": [
					[
						59846.1538461539,
						6,
						0
					],
					[
						60000.0000000001,
						4,
						0
					],
					[
						59384.6153846154,
						6,
						0
					],
					[
						59384.6153846154,
						7,
						0
					],
					[
						59846.1538461539,
						5,
						0
					],
					[
						59076.9230769232,
						3,
						230.769230769231
					],
					[
						59538.4615384616,
						2,
						0
					],
					[
						59538.4615384616,
						1,
						0
					],
					[
						59384.6153846155,
						0,
						0
					],
					[
						59692.3076923078,
						3,
						0
					],
					[
						59846.1538461539,
						1,
						0
					],
					[
						60000.0000000001,
						2,
						0
					],
					[
						60153.8461538462,
						0,
						0
					]
				],
				"mustHitSection": false
			},
			{
				"typeOfSection": 0,
				"lengthInSteps": 16,
				"sectionNotes": [
					[
						60307.6923076924,
						6,
						538.461538461538
					],
					[
						60307.6923076924,
						5,
						0
					],
					[
						60923.076923077,
						7,
						538.461538461538
					],
					[
						60923.076923077,
						4,
						0
					],
					[
						60307.6923076924,
						2,
						0
					],
					[
						60461.5384615385,
						1,
						0
					],
					[
						60615.3846153847,
						0,
						0
					],
					[
						60769.2307692309,
						3,
						0
					],
					[
						60923.076923077,
						0,
						0
					],
					[
						60923.076923077,
						2,
						230.769230769231
					],
					[
						61230.7692307693,
						1,
						230.769230769231
					]
				],
				"mustHitSection": false
			},
			{
				"typeOfSection": 0,
				"lengthInSteps": 16,
				"sectionNotes": [
					[
						61538.4615384616,
						5,
						0
					],
					[
						61692.3076923078,
						6,
						0
					],
					[
						61846.1538461539,
						4,
						0
					],
					[
						62153.8461538462,
						6,
						0
					],
					[
						62153.8461538462,
						7,
						0
					],
					[
						62307.6923076924,
						5,
						0
					],
					[
						62461.5384615385,
						4,
						230.769230769231
					],
					[
						61846.1538461539,
						7,
						0
					],
					[
						62461.5384615385,
						7,
						230.769230769231
					],
					[
						61846.1538461539,
						2,
						230.769230769231
					],
					[
						62153.8461538462,
						1,
						0
					],
					[
						62153.8461538462,
						3,
						0
					],
					[
						62307.6923076924,
						0,
						0
					],
					[
						62615.3846153847,
						2,
						0
					],
					[
						61538.4615384616,
						0,
						0
					],
					[
						61692.3076923078,
						3,
						0
					]
				],
				"mustHitSection": false
			},
			{
				"typeOfSection": 0,
				"lengthInSteps": 16,
				"sectionNotes": [
					[
						62769.2307692308,
						6,
						538.461538461538
					],
					[
						63384.6153846155,
						4,
						0
					],
					[
						63384.6153846155,
						5,
						538.461538461538
					],
					[
						63384.6153846155,
						2,
						538.461538461538
					],
					[
						62769.2307692309,
						1,
						538.461538461538
					],
					[
						62769.2307692309,
						0,
						538.461538461538
					],
					[
						63384.6153846155,
						3,
						538.461538461538
					]
				],
				"mustHitSection": false
			},
			{
				"typeOfSection": 0,
				"lengthInSteps": 16,
				"sectionNotes": [
					[
						64769.2307692308,
						6,
						0
					],
					[
						64923.076923077,
						4,
						0
					],
					[
						64307.6923076924,
						6,
						0
					],
					[
						64307.6923076924,
						7,
						0
					],
					[
						64769.2307692308,
						5,
						0
					],
					[
						64000.0000000001,
						3,
						230.769230769231
					],
					[
						64461.5384615385,
						2,
						0
					],
					[
						64461.5384615385,
						1,
						0
					],
					[
						64307.6923076924,
						0,
						0
					],
					[
						64615.3846153847,
						3,
						0
					],
					[
						64769.2307692308,
						1,
						0
					],
					[
						64923.076923077,
						2,
						0
					],
					[
						65076.9230769232,
						0,
						0
					]
				],
				"mustHitSection": true
			},
			{
				"typeOfSection": 0,
				"lengthInSteps": 16,
				"sectionNotes": [
					[
						65230.7692307693,
						6,
						538.461538461538
					],
					[
						65230.7692307693,
						5,
						0
					],
					[
						65846.1538461539,
						7,
						538.461538461538
					],
					[
						65846.1538461539,
						4,
						0
					],
					[
						65230.7692307693,
						2,
						0
					],
					[
						65384.6153846155,
						1,
						0
					],
					[
						65538.4615384616,
						0,
						0
					],
					[
						65692.3076923078,
						3,
						0
					],
					[
						65846.1538461539,
						0,
						0
					],
					[
						65846.1538461539,
						2,
						230.769230769231
					],
					[
						66153.8461538462,
						1,
						230.769230769231
					]
				],
				"mustHitSection": true
			},
			{
				"typeOfSection": 0,
				"lengthInSteps": 16,
				"sectionNotes": [
					[
						66461.5384615385,
						5,
						0
					],
					[
						66615.3846153847,
						6,
						0
					],
					[
						66769.2307692308,
						4,
						0
					],
					[
						67076.9230769232,
						6,
						0
					],
					[
						67076.9230769232,
						7,
						0
					],
					[
						67230.7692307693,
						5,
						0
					],
					[
						67384.6153846155,
						4,
						230.769230769231
					],
					[
						66769.2307692308,
						7,
						0
					],
					[
						67384.6153846155,
						7,
						230.769230769231
					],
					[
						66769.2307692309,
						2,
						230.769230769231
					],
					[
						67076.9230769232,
						1,
						0
					],
					[
						67076.9230769232,
						3,
						0
					],
					[
						67230.7692307693,
						0,
						0
					],
					[
						67538.4615384616,
						2,
						0
					],
					[
						66461.5384615385,
						0,
						0
					],
					[
						66615.3846153847,
						3,
						0
					]
				],
				"mustHitSection": true
			},
			{
				"typeOfSection": 0,
				"lengthInSteps": 16,
				"sectionNotes": [
					[
						67692.3076923078,
						6,
						538.461538461538
					],
					[
						68307.6923076924,
						4,
						0
					],
					[
						68307.6923076924,
						5,
						538.461538461538
					],
					[
						68307.6923076924,
						2,
						538.461538461538
					],
					[
						67692.3076923078,
						1,
						538.461538461538
					],
					[
						67692.3076923078,
						0,
						538.461538461538
					],
					[
						68307.6923076924,
						3,
						538.461538461538
					]
				],
				"mustHitSection": true
			},
			{
				"typeOfSection": 0,
				"lengthInSteps": 16,
				"sectionNotes": [
					[
						68923.076923077,
						2,
						230.769230769231
					],
					[
						69230.7692307693,
						3,
						0
					],
					[
						69230.7692307693,
						1,
						0
					],
					[
						69384.6153846155,
						0,
						0
					],
					[
						69538.4615384616,
						1,
						0
					],
					[
						69692.3076923078,
						2,
						0
					],
					[
						69846.1538461539,
						3,
						0
					],
					[
						69846.1538461539,
						0,
						0
					],
					[
						70000.0000000001,
						1,
						0
					]
				],
				"mustHitSection": false
			},
			{
				"typeOfSection": 0,
				"lengthInSteps": 16,
				"sectionNotes": [
					[
						70538.4615384616,
						1,
						0
					],
					[
						70615.3846153847,
						2,
						0
					],
					[
						70692.3076923078,
						1,
						0
					],
					[
						70769.2307692309,
						3,
						538.461538461538
					],
					[
						70461.5384615386,
						3,
						0
					],
					[
						70461.5384615386,
						2,
						0
					],
					[
						70615.3846153847,
						0,
						0
					],
					[
						70153.8461538463,
						0,
						230.769230769231
					]
				],
				"mustHitSection": false
			},
			{
				"typeOfSection": 0,
				"lengthInSteps": 16,
				"sectionNotes": [
					[
						71384.6153846155,
						1,
						230.769230769231
					],
					[
						71384.6153846155,
						0,
						0
					],
					[
						71692.3076923078,
						3,
						0
					],
					[
						71846.153846154,
						1,
						0
					],
					[
						72000.0000000001,
						2,
						0
					],
					[
						72307.6923076924,
						2,
						0
					],
					[
						72307.6923076924,
						3,
						0
					],
					[
						72461.5384615386,
						0,
						0
					]
				],
				"mustHitSection": false
			},
			{
				"typeOfSection": 0,
				"lengthInSteps": 16,
				"sectionNotes": [
					[
						72615.3846153847,
						1,
						538.461538461538
					],
					[
						73230.7692307693,
						3,
						538.461538461538
					]
				],
				"mustHitSection": false
			},
			{
				"typeOfSection": 0,
				"lengthInSteps": 16,
				"sectionNotes": [
					[
						73846.1538461539,
						1,
						230.769230769231
					],
					[
						74153.8461538463,
						0,
						0
					],
					[
						74153.8461538463,
						2,
						0
					],
					[
						74307.6923076924,
						3,
						0
					],
					[
						74461.5384615386,
						2,
						0
					],
					[
						74615.3846153847,
						1,
						0
					],
					[
						74769.2307692309,
						0,
						0
					],
					[
						74769.2307692309,
						3,
						0
					],
					[
						74923.076923077,
						2,
						0
					]
				],
				"mustHitSection": true
			},
			{
				"typeOfSection": 0,
				"lengthInSteps": 16,
				"sectionNotes": [
					[
						75461.5384615386,
						2,
						0
					],
					[
						75538.4615384616,
						1,
						0
					],
					[
						75615.3846153847,
						2,
						0
					],
					[
						75692.3076923078,
						0,
						538.461538461538
					],
					[
						75384.6153846155,
						0,
						0
					],
					[
						75384.6153846155,
						1,
						0
					],
					[
						75538.4615384616,
						3,
						0
					],
					[
						75076.9230769232,
						3,
						230.769230769231
					]
				],
				"mustHitSection": true
			},
			{
				"typeOfSection": 0,
				"lengthInSteps": 16,
				"sectionNotes": [
					[
						76307.6923076924,
						2,
						230.769230769231
					],
					[
						76307.6923076924,
						3,
						0
					],
					[
						76615.3846153847,
						0,
						0
					],
					[
						76769.2307692309,
						2,
						0
					],
					[
						76923.076923077,
						1,
						0
					],
					[
						77230.7692307693,
						1,
						0
					],
					[
						77230.7692307693,
						0,
						0
					],
					[
						77384.6153846155,
						3,
						0
					]
				],
				"mustHitSection": true
			},
			{
				"typeOfSection": 0,
				"lengthInSteps": 16,
				"sectionNotes": [
					[
						77538.4615384616,
						2,
						538.461538461538
					],
					[
						78153.8461538463,
						0,
						538.461538461538
					]
				],
				"mustHitSection": true
			},
			{
				"typeOfSection": 0,
				"lengthInSteps": 16,
				"sectionNotes": [
					[
						79076.9230769232,
						3,
						230.769230769231
					],
					[
						79538.4615384617,
						1,
						0
					],
					[
						79692.3076923078,
						3,
						0
					],
					[
						79692.3076923078,
						2,
						0
					],
					[
						79846.153846154,
						1,
						76.9230769230769
					]
				],
				"mustHitSection": false
			},
			{
				"typeOfSection": 0,
				"lengthInSteps": 16,
				"sectionNotes": [
					[
						80615.3846153848,
						0,
						230.769230769231
					],
					[
						80923.0769230771,
						2,
						0
					],
					[
						80923.0769230771,
						3,
						0
					],
					[
						81076.9230769232,
						1,
						0
					],
					[
						80000.0000000001,
						0,
						153.846153846154
					],
					[
						80230.7692307694,
						2,
						153.846153846154
					],
					[
						80461.5384615386,
						3,
						0
					]
				],
				"mustHitSection": false
			},
			{
				"typeOfSection": 0,
				"lengthInSteps": 16,
				"sectionNotes": [
					[
						81230.7692307694,
						2,
						230.769230769231
					],
					[
						81538.4615384617,
						3,
						230.769230769231
					],
					[
						81538.4615384617,
						1,
						230.769230769231
					],
					[
						81846.153846154,
						0,
						230.769230769231
					],
					[
						82153.8461538463,
						0,
						0
					],
					[
						82153.8461538463,
						2,
						230.769230769231
					]
				],
				"mustHitSection": false
			},
			{
				"typeOfSection": 0,
				"lengthInSteps": 16,
				"sectionNotes": [
					[
						82461.5384615386,
						1,
						230.769230769231
					],
					[
						82923.0769230771,
						3,
						0
					],
					[
						82923.0769230771,
						2,
						0
					],
					[
						83076.9230769232,
						0,
						0
					],
					[
						83076.9230769232,
						1,
						0
					],
					[
						83230.7692307694,
						2,
						0
					],
					[
						83384.6153846155,
						0,
						230.769230769231
					]
				],
				"mustHitSection": false
			},
			{
				"typeOfSection": 0,
				"lengthInSteps": 16,
				"sectionNotes": [
					[
						84000.0000000001,
						0,
						230.769230769231
					],
					[
						84461.5384615386,
						2,
						0
					],
					[
						84615.3846153847,
						0,
						0
					],
					[
						84615.3846153847,
						1,
						0
					],
					[
						84769.2307692309,
						2,
						76.9230769230769
					]
				],
				"mustHitSection": true
			},
			{
				"typeOfSection": 0,
				"lengthInSteps": 16,
				"sectionNotes": [
					[
						85538.4615384617,
						3,
						230.769230769231
					],
					[
						85846.153846154,
						1,
						0
					],
					[
						85846.153846154,
						0,
						0
					],
					[
						86000.0000000001,
						2,
						0
					],
					[
						84923.0769230771,
						3,
						153.846153846154
					],
					[
						85153.8461538463,
						1,
						153.846153846154
					],
					[
						85384.6153846155,
						0,
						0
					]
				],
				"mustHitSection": true
			},
			{
				"typeOfSection": 0,
				"lengthInSteps": 16,
				"sectionNotes": [
					[
						86153.8461538463,
						5,
						230.769230769231
					],
					[
						86461.5384615386,
						4,
						230.769230769231
					],
					[
						86461.5384615386,
						6,
						230.769230769231
					],
					[
						86769.2307692309,
						7,
						230.769230769231
					],
					[
						87076.9230769232,
						5,
						230.769230769231
					],
					[
						87076.9230769232,
						7,
						0
					]
				],
				"mustHitSection": false
			},
			{
				"typeOfSection": 0,
				"lengthInSteps": 16,
				"sectionNotes": [
					[
						87384.6153846155,
						6,
						230.769230769231
					],
					[
						87846.153846154,
						4,
						0
					],
					[
						87846.153846154,
						5,
						0
					],
					[
						88000.0000000001,
						7,
						0
					],
					[
						88000.0000000001,
						6,
						0
					],
					[
						88153.8461538463,
						5,
						0
					],
					[
						88307.6923076924,
						7,
						230.769230769231
					]
				],
				"mustHitSection": false
			},
			{
				"typeOfSection": 0,
				"lengthInSteps": 16,
				"sectionNotes": [
					[
						88615.3846153848,
						3,
						538.461538461538
					],
					[
						88615.3846153848,
						0,
						538.461538461538
					],
					[
						89230.7692307694,
						2,
						230.769230769231
					],
					[
						89538.4615384617,
						0,
						230.769230769231
					],
					[
						89230.7692307694,
						1,
						230.769230769231
					],
					[
						89538.4615384617,
						1,
						230.769230769231
					]
				],
				"mustHitSection": false
			},
			{
				"typeOfSection": 0,
				"lengthInSteps": 16,
				"sectionNotes": [
					[
						89846.153846154,
						3,
						230.769230769231
					],
					[
						89846.153846154,
						2,
						230.769230769231
					],
					[
						90153.8461538463,
						1,
						0
					],
					[
						90307.6923076925,
						3,
						0
					],
					[
						90461.5384615386,
						0,
						230.769230769231
					],
					[
						90769.2307692309,
						2,
						230.769230769231
					],
					[
						90769.2307692309,
						1,
						230.769230769231
					]
				],
				"mustHitSection": false
			},
			{
				"typeOfSection": 0,
				"lengthInSteps": 16,
				"sectionNotes": [
					[
						91076.9230769232,
						3,
						538.461538461538
					],
					[
						91076.9230769232,
						0,
						538.461538461538
					],
					[
						91692.3076923078,
						2,
						230.769230769231
					],
					[
						92000.0000000001,
						0,
						230.769230769231
					],
					[
						91692.3076923078,
						1,
						230.769230769231
					],
					[
						92000.0000000001,
						1,
						230.769230769231
					]
				],
				"mustHitSection": true
			},
			{
				"typeOfSection": 0,
				"lengthInSteps": 16,
				"sectionNotes": [
					[
						92307.6923076925,
						3,
						230.769230769231
					],
					[
						92307.6923076925,
						2,
						230.769230769231
					],
					[
						92615.3846153848,
						1,
						0
					],
					[
						92769.2307692309,
						3,
						0
					],
					[
						92923.0769230771,
						0,
						230.769230769231
					],
					[
						93230.7692307694,
						2,
						230.769230769231
					],
					[
						93230.7692307694,
						1,
						230.769230769231
					]
				],
				"mustHitSection": true
			},
			{
				"typeOfSection": 0,
				"lengthInSteps": 16,
				"sectionNotes": [
					[
						93538.4615384617,
						3,
						384.615384615385
					],
					[
						94000.0000000002,
						0,
						0
					],
					[
						94153.8461538463,
						0,
						0
					],
					[
						94153.8461538463,
						4,
						0
					],
					[
						94000.0000000002,
						4,
						0
					],
					[
						94461.5384615386,
						0,
						230.769230769231
					],
					[
						94461.5384615386,
						4,
						230.769230769231
					],
					[
						94000.0000000002,
						1,
						0
					],
					[
						94153.8461538463,
						2,
						0
					],
					[
						94461.5384615386,
						3,
						0
					],
					[
						93538.4615384617,
						7,
						384.615384615385
					],
					[
						94000.0000000002,
						4,
						0
					],
					[
						94153.8461538463,
						4,
						0
					],
					[
						94153.8461538463,
						0,
						0
					],
					[
						94000.0000000002,
						0,
						0
					],
					[
						94461.5384615386,
						4,
						230.769230769231
					],
					[
						94461.5384615386,
						0,
						230.769230769231
					],
					[
						94000.0000000002,
						5,
						0
					],
					[
						94153.8461538463,
						6,
						0
					],
					[
						94461.5384615386,
						7,
						0
					]
				],
				"mustHitSection": true
			},
			{
				"typeOfSection": 0,
				"lengthInSteps": 16,
				"sectionNotes": [
					[
						94769.2307692309,
						1,
						384.615384615385
					],
					[
						95230.7692307694,
						3,
						0
					],
					[
						95384.6153846155,
						1,
						0
					],
					[
						95384.6153846155,
						2,
						0
					],
					[
						95538.4615384617,
						0,
						0
					],
					[
						95692.3076923078,
						1,
						230.769230769231
					],
					[
						94769.2307692309,
						5,
						384.615384615385
					],
					[
						95230.7692307694,
						7,
						0
					],
					[
						95384.6153846155,
						5,
						0
					],
					[
						95384.6153846155,
						6,
						0
					],
					[
						95538.4615384617,
						4,
						0
					],
					[
						95692.3076923078,
						5,
						230.769230769231
					]
				],
				"mustHitSection": true
			},
			{
				"typeOfSection": 0,
				"lengthInSteps": 16,
				"sectionNotes": [
					[
						96000.0000000002,
						2,
						230.769230769231
					],
					[
						96307.6923076925,
						3,
						0
					],
					[
						96461.5384615386,
						1,
						0
					],
					[
						96615.3846153848,
						0,
						0
					],
					[
						96769.2307692309,
						3,
						0
					],
					[
						96923.0769230771,
						1,
						230.769230769231
					],
					[
						96923.0769230771,
						2,
						0
					],
					[
						96000.0000000002,
						6,
						230.769230769231
					],
					[
						96307.6923076925,
						7,
						0
					],
					[
						96461.5384615386,
						5,
						0
					],
					[
						96615.3846153848,
						4,
						0
					],
					[
						96769.2307692309,
						7,
						0
					],
					[
						96923.0769230771,
						5,
						230.769230769231
					],
					[
						96923.0769230771,
						6,
						0
					]
				],
				"mustHitSection": false
			},
			{
				"typeOfSection": 0,
				"lengthInSteps": 16,
				"sectionNotes": [
					[
						97230.7692307694,
						4,
						1153.84615384615
					],
					[
						97538.4615384617,
						7,
						846.153846153846
					],
					[
						97692.3076923079,
						6,
						692.307692307692
					],
					[
						97846.153846154,
						5,
						538.461538461538
					],
					[
						97230.7692307694,
						0,
						1153.84615384615
					],
					[
						97538.4615384617,
						3,
						846.153846153846
					],
					[
						97692.3076923079,
						2,
						692.307692307692
					],
					[
						97846.153846154,
						1,
						538.461538461538
					]
				],
				"mustHitSection": false
			},
			{
				"typeOfSection": 0,
				"lengthInSteps": 16,
				"sectionNotes": [
					[
						98461.5384615386,
						0,
						0
					],
					[
						98538.4615384617,
						2,
						0
					],
					[
						98615.3846153848,
						1,
						0
					],
					[
						98692.3076923079,
						0,
						0
					],
					[
						98769.2307692309,
						1,
						0
					],
					[
						98769.2307692309,
						3,
						0
					],
					[
						98923.0769230771,
						0,
						0
					],
					[
						99076.9230769232,
						2,
						0
					],
					[
						99307.6923076925,
						0,
						0
					],
					[
						99307.6923076925,
						3,
						0
					],
					[
						99538.4615384617,
						1,
						0
					]
				],
				"mustHitSection": false
			},
			{
				"typeOfSection": 0,
				"lengthInSteps": 16,
				"sectionNotes": [
					[
						99692.3076923079,
						0,
						0
					],
					[
						99692.3076923079,
						3,
						0
					],
					[
						99769.2307692309,
						1,
						0
					],
					[
						99846.153846154,
						3,
						0
					],
					[
						99923.0769230771,
						0,
						0
					],
					[
						100000,
						1,
						0
					],
					[
						100000,
						2,
						0
					],
					[
						100153.846153846,
						2,
						0
					],
					[
						100307.692307692,
						3,
						0
					],
					[
						100538.461538462,
						0,
						0
					],
					[
						100307.692307692,
						1,
						0
					],
					[
						100538.461538462,
						2,
						0
					],
					[
						100769.230769231,
						1,
						0
					],
					[
						100769.230769231,
						3,
						0
					]
				],
				"mustHitSection": false
			},
			{
				"typeOfSection": 0,
				"lengthInSteps": 16,
				"sectionNotes": [
					[
						100923.076923077,
						0,
						0
					],
					[
						101076.923076923,
						2,
						0
					],
					[
						101230.769230769,
						1,
						230.769230769231
					],
					[
						101230.769230769,
						3,
						0
					],
					[
						101538.461538462,
						0,
						230.769230769231
					],
					[
						101846.153846154,
						2,
						0
					],
					[
						101846.153846154,
						3,
						0
					],
					[
						102000,
						1,
						0
					]
				],
				"mustHitSection": false
			},
			{
				"typeOfSection": 0,
				"lengthInSteps": 16,
				"sectionNotes": [
					[
						102153.846153846,
						0,
						538.461538461538
					],
					[
						102153.846153846,
						2,
						0
					],
					[
						102769.230769231,
						3,
						538.461538461538
					]
				],
				"mustHitSection": false
			},
			{
				"typeOfSection": 0,
				"lengthInSteps": 16,
				"sectionNotes": [
					[
						103384.615384616,
						0,
						0
					],
					[
						103461.538461539,
						2,
						0
					],
					[
						103538.461538462,
						1,
						0
					],
					[
						103615.384615385,
						0,
						0
					],
					[
						103692.307692308,
						1,
						0
					],
					[
						103692.307692308,
						3,
						0
					],
					[
						103846.153846154,
						0,
						0
					],
					[
						104000,
						2,
						0
					],
					[
						104230.769230769,
						0,
						0
					],
					[
						104230.769230769,
						3,
						0
					],
					[
						104461.538461539,
						1,
						0
					],
					[
						103384.615384616,
						6,
						384.615384615385
					],
					[
						103384.615384616,
						5,
						0
					]
				],
				"mustHitSection": true
			},
			{
				"typeOfSection": 0,
				"lengthInSteps": 16,
				"sectionNotes": [
					[
						104615.384615385,
						0,
						0
					],
					[
						104615.384615385,
						3,
						0
					],
					[
						104692.307692308,
						1,
						0
					],
					[
						104769.230769231,
						3,
						0
					],
					[
						104846.153846154,
						0,
						0
					],
					[
						104923.076923077,
						1,
						0
					],
					[
						104923.076923077,
						2,
						0
					],
					[
						105076.923076923,
						2,
						0
					],
					[
						105230.769230769,
						3,
						0
					],
					[
						105461.538461539,
						0,
						0
					],
					[
						105230.769230769,
						1,
						0
					],
					[
						105461.538461539,
						2,
						0
					],
					[
						105692.307692308,
						1,
						0
					],
					[
						105692.307692308,
						3,
						0
					]
				],
				"mustHitSection": true
			},
			{
				"typeOfSection": 0,
				"lengthInSteps": 16,
				"sectionNotes": [
					[
						105846.153846154,
						0,
						0
					],
					[
						106000,
						2,
						0
					],
					[
						106153.846153846,
						1,
						230.769230769231
					],
					[
						106153.846153846,
						3,
						0
					],
					[
						106461.538461539,
						0,
						230.769230769231
					],
					[
						106769.230769231,
						2,
						0
					],
					[
						106769.230769231,
						3,
						0
					],
					[
						106923.076923077,
						1,
						0
					]
				],
				"mustHitSection": true
			},
			{
				"typeOfSection": 0,
				"lengthInSteps": 16,
				"sectionNotes": [
					[
						107076.923076923,
						0,
						538.461538461538
					],
					[
						107076.923076923,
						2,
						0
					],
					[
						107692.307692308,
						3,
						538.461538461538
					]
				],
				"mustHitSection": true
			},
			{
				"typeOfSection": 0,
				"lengthInSteps": 16,
				"sectionNotes": [
					[
						108307.692307693,
						0,
						0
					],
					[
						108307.692307693,
						3,
						0
					],
					[
						108461.538461539,
						1,
						0
					],
					[
						108615.384615385,
						0,
						0
					],
					[
						108615.384615385,
						2,
						0
					],
					[
						108769.230769231,
						3,
						0
					],
					[
						108923.076923077,
						2,
						0
					],
					[
						109000,
						1,
						0
					],
					[
						109076.923076923,
						0,
						0
					],
					[
						109153.846153846,
						2,
						0
					],
					[
						109230.769230769,
						1,
						0
					],
					[
						109230.769230769,
						3,
						0
					],
					[
						109307.692307693,
						2,
						0
					],
					[
						109384.615384616,
						3,
						0
					],
					[
						109461.538461539,
						2,
						0
					]
				],
				"mustHitSection": false
			},
			{
				"typeOfSection": 0,
				"lengthInSteps": 16,
				"sectionNotes": [
					[
						109538.461538462,
						0,
						0
					],
					[
						109538.461538462,
						3,
						0
					],
					[
						109692.307692308,
						1,
						0
					],
					[
						109846.153846154,
						0,
						0
					],
					[
						109846.153846154,
						2,
						0
					],
					[
						110000,
						3,
						0
					],
					[
						110153.846153846,
						0,
						0
					],
					[
						110230.769230769,
						1,
						0
					],
					[
						110307.692307693,
						0,
						0
					],
					[
						110384.615384616,
						1,
						0
					],
					[
						110461.538461539,
						0,
						0
					],
					[
						110461.538461539,
						2,
						0
					],
					[
						110538.461538462,
						1,
						0
					],
					[
						110615.384615385,
						3,
						0
					],
					[
						110692.307692308,
						2,
						0
					]
				],
				"mustHitSection": false
			},
			{
				"typeOfSection": 0,
				"lengthInSteps": 16,
				"sectionNotes": [
					[
						110769.230769231,
						0,
						0
					],
					[
						110769.230769231,
						1,
						0
					],
					[
						110923.076923077,
						3,
						0
					],
					[
						111076.923076923,
						3,
						0
					],
					[
						111076.923076923,
						2,
						0
					],
					[
						111230.769230769,
						1,
						0
					],
					[
						111384.615384616,
						3,
						0
					],
					[
						111538.461538462,
						0,
						0
					],
					[
						111538.461538462,
						2,
						0
					],
					[
						111692.307692308,
						1,
						0
					],
					[
						111692.307692308,
						2,
						230.769230769231
					]
				],
				"mustHitSection": false
			},
			{
				"typeOfSection": 0,
				"lengthInSteps": 16,
				"sectionNotes": [
					[
						112000,
						0,
						230.769230769231
					],
					[
						112307.692307693,
						1,
						0
					],
					[
						112307.692307693,
						3,
						0
					],
					[
						112461.538461539,
						2,
						0
					],
					[
						112615.384615385,
						1,
						538.461538461538
					]
				],
				"mustHitSection": false
			},
			{
				"typeOfSection": 0,
				"lengthInSteps": 16,
				"sectionNotes": [
					[
						113230.769230769,
						0,
						0
					],
					[
						113230.769230769,
						3,
						0
					],
					[
						113384.615384616,
						1,
						0
					],
					[
						113538.461538462,
						0,
						0
					],
					[
						113538.461538462,
						2,
						0
					],
					[
						113692.307692308,
						3,
						0
					],
					[
						113846.153846154,
						2,
						0
					],
					[
						113923.076923077,
						1,
						0
					],
					[
						114000,
						0,
						0
					],
					[
						114076.923076923,
						2,
						0
					],
					[
						114153.846153846,
						1,
						0
					],
					[
						114153.846153846,
						3,
						0
					],
					[
						114230.769230769,
						2,
						0
					],
					[
						114307.692307693,
						3,
						0
					],
					[
						114384.615384616,
						2,
						0
					]
				],
				"mustHitSection": true
			},
			{
				"typeOfSection": 0,
				"lengthInSteps": 16,
				"sectionNotes": [
					[
						114461.538461539,
						0,
						0
					],
					[
						114461.538461539,
						3,
						0
					],
					[
						114615.384615385,
						1,
						0
					],
					[
						114769.230769231,
						0,
						0
					],
					[
						114769.230769231,
						2,
						0
					],
					[
						114923.076923077,
						3,
						0
					],
					[
						115076.923076923,
						0,
						0
					],
					[
						115153.846153846,
						1,
						0
					],
					[
						115230.769230769,
						0,
						0
					],
					[
						115307.692307693,
						1,
						0
					],
					[
						115384.615384616,
						0,
						0
					],
					[
						115384.615384616,
						2,
						0
					],
					[
						115461.538461539,
						1,
						0
					],
					[
						115538.461538462,
						3,
						0
					],
					[
						115615.384615385,
						2,
						0
					]
				],
				"mustHitSection": true
			},
			{
				"typeOfSection": 0,
				"lengthInSteps": 16,
				"sectionNotes": [
					[
						115692.307692308,
						0,
						0
					],
					[
						115692.307692308,
						1,
						0
					],
					[
						115846.153846154,
						3,
						0
					],
					[
						116000,
						3,
						0
					],
					[
						116000,
						2,
						0
					],
					[
						116153.846153846,
						1,
						0
					],
					[
						116307.692307693,
						3,
						0
					],
					[
						116461.538461539,
						0,
						0
					],
					[
						116461.538461539,
						2,
						0
					],
					[
						116615.384615385,
						1,
						0
					],
					[
						116615.384615385,
						2,
						230.769230769231
					]
				],
				"mustHitSection": true
			},
			{
				"typeOfSection": 0,
				"lengthInSteps": 16,
				"sectionNotes": [
					[
						116923.076923077,
						0,
						230.769230769231
					],
					[
						117230.769230769,
						1,
						0
					],
					[
						117230.769230769,
						3,
						0
					],
					[
						117384.615384616,
						2,
						0
					],
					[
						117538.461538462,
						1,
						538.461538461538
					]
				],
				"mustHitSection": true
			},
			{
				"typeOfSection": 0,
				"lengthInSteps": 16,
				"sectionNotes": [
					[
						118461.538461538,
						3,
						0
					],
					[
						118615.384615385,
						2,
						0
					],
					[
						118153.846153846,
						0,
						230.769230769231
					],
					[
						118153.846153846,
						2,
						0
					],
					[
						118615.384615385,
						1,
						0
					],
					[
						119076.923076923,
						3,
						0
					],
					[
						119230.769230769,
						0,
						0
					],
					[
						118923.076923077,
						1,
						0
					]
				],
				"mustHitSection": false
			},
			{
				"typeOfSection": 0,
				"lengthInSteps": 16,
				"sectionNotes": [
					[
						119384.615384615,
						2,
						230.769230769231
					],
					[
						119384.615384615,
						3,
						0
					],
					[
						119692.307692308,
						0,
						0
					],
					[
						119846.153846154,
						2,
						0
					],
					[
						120000,
						1,
						0
					],
					[
						120000,
						3,
						0
					],
					[
						120153.846153846,
						0,
						0
					],
					[
						120307.692307692,
						2,
						230.769230769231
					]
				],
				"mustHitSection": false
			},
			{
				"typeOfSection": 0,
				"lengthInSteps": 16,
				"sectionNotes": [
					[
						120923.076923077,
						3,
						0
					],
					[
						121076.923076923,
						2,
						0
					],
					[
						120615.384615385,
						0,
						230.769230769231
					],
					[
						120615.384615385,
						2,
						0
					],
					[
						121076.923076923,
						1,
						0
					],
					[
						121538.461538462,
						3,
						0
					],
					[
						121692.307692308,
						0,
						0
					],
					[
						121384.615384615,
						1,
						0
					]
				],
				"mustHitSection": true
			},
			{
				"typeOfSection": 0,
				"lengthInSteps": 16,
				"sectionNotes": [
					[
						121846.153846154,
						2,
						230.769230769231
					],
					[
						121846.153846154,
						3,
						0
					],
					[
						122153.846153846,
						0,
						0
					],
					[
						122307.692307692,
						2,
						0
					],
					[
						122461.538461538,
						1,
						0
					],
					[
						122461.538461538,
						3,
						0
					],
					[
						122615.384615385,
						0,
						0
					],
					[
						122769.230769231,
						2,
						230.769230769231
					]
				],
				"mustHitSection": true
			},
			{
				"typeOfSection": 0,
				"lengthInSteps": 16,
				"sectionNotes": [
					[
						123076.923076923,
						4,
						538.461538461538
					],
					[
						123076.923076923,
						7,
						0
					],
					[
						123692.307692308,
						5,
						538.461538461538
					],
					[
						123692.307692308,
						6,
						0
					],
					[
						123076.923076923,
						2,
						0
					],
					[
						123230.769230769,
						0,
						0
					],
					[
						123384.615384615,
						3,
						0
					],
					[
						123384.615384615,
						1,
						230.769230769231
					],
					[
						123692.307692308,
						0,
						0
					],
					[
						123846.153846154,
						3,
						0
					],
					[
						124000,
						0,
						0
					],
					[
						124000,
						2,
						0
					],
					[
						124153.846153846,
						1,
						0
					]
				],
				"mustHitSection": false
			},
			{
				"typeOfSection": 0,
				"lengthInSteps": 16,
				"sectionNotes": [
					[
						124307.692307692,
						6,
						538.461538461538
					],
					[
						124307.692307692,
						7,
						0
					],
					[
						124923.076923077,
						4,
						230.769230769231
					],
					[
						125230.769230769,
						7,
						230.769230769231
					],
					[
						125230.769230769,
						5,
						0
					],
					[
						124307.692307692,
						0,
						230.769230769231
					],
					[
						124615.384615385,
						2,
						0
					],
					[
						124615.384615385,
						3,
						0
					],
					[
						124769.230769231,
						1,
						0
					],
					[
						124923.076923077,
						2,
						230.769230769231
					],
					[
						125230.769230769,
						0,
						0
					],
					[
						125230.769230769,
						3,
						0
					],
					[
						125384.615384615,
						1,
						0
					]
				],
				"mustHitSection": false
			},
			{
				"typeOfSection": 0,
				"lengthInSteps": 16,
				"sectionNotes": [
					[
						125538.461538462,
						6,
						230.769230769231
					],
					[
						125846.153846154,
						7,
						230.769230769231
					],
					[
						125846.153846154,
						4,
						0
					],
					[
						126153.846153846,
						5,
						230.769230769231
					],
					[
						126461.538461538,
						4,
						0
					],
					[
						126461.538461538,
						6,
						230.769230769231
					],
					[
						125538.461538462,
						0,
						230.769230769231
					],
					[
						125538.461538462,
						2,
						230.769230769231
					],
					[
						125846.153846154,
						1,
						230.769230769231
					],
					[
						125846.153846154,
						3,
						230.769230769231
					],
					[
						126153.846153846,
						2,
						0
					],
					[
						126307.692307692,
						0,
						0
					],
					[
						126461.538461538,
						2,
						230.769230769231
					]
				],
				"mustHitSection": false
			},
			{
				"typeOfSection": 0,
				"lengthInSteps": 16,
				"sectionNotes": [
					[
						126769.230769231,
						5,
						538.461538461538
					],
					[
						127692.307692308,
						4,
						230.769230769231
					],
					[
						127384.615384615,
						7,
						230.769230769231
					],
					[
						127384.615384615,
						6,
						0
					],
					[
						127692.307692308,
						5,
						0
					],
					[
						126769.230769231,
						1,
						230.769230769231
					],
					[
						127076.923076923,
						0,
						0
					],
					[
						127076.923076923,
						3,
						0
					],
					[
						127230.769230769,
						2,
						0
					],
					[
						127384.615384615,
						0,
						538.461538461538
					]
				],
				"mustHitSection": false
			},
			{
				"typeOfSection": 0,
				"lengthInSteps": 16,
				"sectionNotes": [
					[
						128000,
						4,
						538.461538461538
					],
					[
						128000,
						7,
						0
					],
					[
						128615.384615385,
						5,
						538.461538461538
					],
					[
						128615.384615385,
						6,
						0
					],
					[
						128000,
						2,
						0
					],
					[
						128153.846153846,
						0,
						0
					],
					[
						128307.692307692,
						3,
						0
					],
					[
						128307.692307692,
						1,
						230.769230769231
					],
					[
						128615.384615385,
						0,
						0
					],
					[
						128769.230769231,
						3,
						0
					],
					[
						128923.076923077,
						0,
						0
					],
					[
						128923.076923077,
						2,
						0
					],
					[
						129076.923076923,
						1,
						0
					]
				],
				"mustHitSection": true
			},
			{
				"typeOfSection": 0,
				"lengthInSteps": 16,
				"sectionNotes": [
					[
						129230.769230769,
						6,
						538.461538461538
					],
					[
						129230.769230769,
						7,
						0
					],
					[
						129846.153846154,
						4,
						230.769230769231
					],
					[
						130153.846153846,
						7,
						230.769230769231
					],
					[
						130153.846153846,
						5,
						0
					],
					[
						129230.769230769,
						0,
						230.769230769231
					],
					[
						129538.461538462,
						2,
						0
					],
					[
						129538.461538462,
						3,
						0
					],
					[
						129692.307692308,
						1,
						0
					],
					[
						129846.153846154,
						2,
						230.769230769231
					],
					[
						130153.846153846,
						0,
						0
					],
					[
						130153.846153846,
						3,
						0
					],
					[
						130307.692307692,
						1,
						0
					]
				],
				"mustHitSection": true
			},
			{
				"typeOfSection": 0,
				"lengthInSteps": 16,
				"sectionNotes": [
					[
						130461.538461538,
						6,
						230.769230769231
					],
					[
						130769.230769231,
						7,
						230.769230769231
					],
					[
						130769.230769231,
						4,
						0
					],
					[
						131076.923076923,
						5,
						230.769230769231
					],
					[
						131384.615384615,
						4,
						0
					],
					[
						131384.615384615,
						6,
						230.769230769231
					],
					[
						130461.538461538,
						0,
						230.769230769231
					],
					[
						130461.538461538,
						2,
						230.769230769231
					],
					[
						130769.230769231,
						1,
						230.769230769231
					],
					[
						130769.230769231,
						3,
						230.769230769231
					],
					[
						131076.923076923,
						2,
						0
					],
					[
						131230.769230769,
						0,
						0
					],
					[
						131384.615384615,
						2,
						230.769230769231
					]
				],
				"mustHitSection": true
			},
			{
				"typeOfSection": 0,
				"lengthInSteps": 16,
				"sectionNotes": [
					[
						131692.307692308,
						5,
						538.461538461538
					],
					[
						132307.692307692,
						6,
						0
					],
					[
						131692.307692308,
						1,
						230.769230769231
					],
					[
						132000,
						0,
						0
					],
					[
						132000,
						3,
						0
					],
					[
						132153.846153846,
						2,
						0
					],
					[
						132307.692307692,
						0,
						538.461538461538
					],
					[
						132307.692307692,
						7,
						538.461538461538
					]
				],
				"mustHitSection": true
			},
			{
				"typeOfSection": 0,
				"lengthInSteps": 16,
				"sectionNotes": [
					[
						133230.769230769,
						2,
						0
					],
					[
						133538.461538462,
						3,
						0
					],
					[
						133538.461538462,
						1,
						0
					],
					[
						133692.307692308,
						0,
						0
					],
					[
						134000,
						2,
						0
					],
					[
						132923.076923077,
						0,
						0
					],
					[
						132923.076923077,
						1,
						0
					],
					[
						132923.076923077,
						3,
						0
					],
					[
						133230.769230769,
						0,
						0
					],
					[
						133230.769230769,
						3,
						0
					]
				],
				"mustHitSection": false
			},
			{
				"typeOfSection": 0,
				"lengthInSteps": 16,
				"sectionNotes": [
					[
						134153.846153846,
						1,
						230.769230769231
					],
					[
						134461.538461539,
						3,
						230.769230769231
					],
					[
						134461.538461539,
						0,
						0
					],
					[
						134769.230769231,
						2,
						0
					],
					[
						134769.230769231,
						1,
						0
					],
					[
						134846.153846154,
						0,
						0
					],
					[
						134923.076923077,
						1,
						0
					],
					[
						135000,
						2,
						0
					],
					[
						135076.923076923,
						3,
						0
					],
					[
						135230.769230769,
						1,
						0
					],
					[
						135076.923076923,
						0,
						0
					]
				],
				"mustHitSection": false
			},
			{
				"typeOfSection": 0,
				"lengthInSteps": 16,
				"sectionNotes": [
					[
						135384.615384615,
						0,
						230.769230769231
					],
					[
						135384.615384615,
						2,
						0
					],
					[
						135692.307692308,
						1,
						0
					],
					[
						135692.307692308,
						3,
						230.769230769231
					],
					[
						136000,
						2,
						0
					],
					[
						136000,
						1,
						0
					],
					[
						136153.846153846,
						0,
						0
					],
					[
						136307.692307692,
						2,
						0
					],
					[
						136461.538461539,
						1,
						0
					]
				],
				"mustHitSection": false
			},
			{
				"typeOfSection": 0,
				"lengthInSteps": 16,
				"sectionNotes": [
					[
						136615.384615385,
						3,
						0
					],
					[
						136653.846153846,
						2,
						0
					],
					[
						137230.769230769,
						2,
						538.461538461538
					],
					[
						136923.076923077,
						1,
						0
					]
				],
				"mustHitSection": false
			},
			{
				"typeOfSection": 0,
				"lengthInSteps": 16,
				"sectionNotes": [
					[
						137846.153846154,
						2,
						0
					],
					[
						138461.538461539,
						0,
						0
					],
					[
						138461.538461539,
						2,
						0
					],
					[
						138615.384615385,
						3,
						0
					],
					[
						138923.076923077,
						1,
						0
					],
					[
						137846.153846154,
						0,
						0
					],
					[
						137846.153846154,
						3,
						0
					],
					[
						138153.846153846,
						0,
						0
					],
					[
						138153.846153846,
						1,
						0
					],
					[
						138153.846153846,
						3,
						0
					]
				],
				"mustHitSection": true
			},
			{
				"typeOfSection": 0,
				"lengthInSteps": 16,
				"sectionNotes": [
					[
						139076.923076923,
						2,
						230.769230769231
					],
					[
						139384.615384615,
						0,
						230.769230769231
					],
					[
						139384.615384615,
						3,
						0
					],
					[
						139692.307692308,
						1,
						0
					],
					[
						139692.307692308,
						2,
						0
					],
					[
						139769.230769231,
						3,
						0
					],
					[
						139846.153846154,
						2,
						0
					],
					[
						139923.076923077,
						1,
						0
					],
					[
						140000,
						0,
						0
					],
					[
						140153.846153846,
						2,
						0
					],
					[
						140000,
						3,
						0
					]
				],
				"mustHitSection": true
			},
			{
				"typeOfSection": 0,
				"lengthInSteps": 16,
				"sectionNotes": [
					[
						140307.692307692,
						3,
						230.769230769231
					],
					[
						140307.692307692,
						1,
						0
					],
					[
						140615.384615385,
						2,
						0
					],
					[
						140615.384615385,
						0,
						230.769230769231
					],
					[
						140923.076923077,
						1,
						0
					],
					[
						140923.076923077,
						2,
						0
					],
					[
						141076.923076923,
						3,
						0
					],
					[
						141230.769230769,
						1,
						0
					],
					[
						141384.615384615,
						2,
						0
					]
				],
				"mustHitSection": true
			},
			{
				"typeOfSection": 0,
				"lengthInSteps": 16,
				"sectionNotes": [
					[
						141538.461538462,
						0,
						0
					],
					[
						141576.923076923,
						1,
						0
					],
					[
						142153.846153846,
						1,
						538.461538461538
					],
					[
						141846.153846154,
						2,
						0
					]
				],
				"mustHitSection": true
			},
			{
				"typeOfSection": 0,
				"lengthInSteps": 16,
				"sectionNotes": [
					[
						143076.923076923,
						4,
						0
					],
					[
						143230.769230769,
						6,
						0
					],
					[
						143384.615384615,
						5,
						230.769230769231
					],
					[
						143384.615384615,
						7,
						0
					],
					[
						143692.307692308,
						4,
						0
					],
					[
						143846.153846154,
						6,
						0
					],
					[
						142769.230769231,
						6,
						230.769230769231
					],
					[
						142769.230769231,
						7,
						230.769230769231
					],
					[
						143076.923076923,
						0,
						0
					],
					[
						143230.769230769,
						2,
						0
					],
					[
						143384.615384615,
						1,
						230.769230769231
					],
					[
						143384.615384615,
						3,
						0
					],
					[
						143692.307692308,
						0,
						0
					],
					[
						143846.153846154,
						2,
						0
					],
					[
						142769.230769231,
						2,
						230.769230769231
					],
					[
						142769.230769231,
						3,
						230.769230769231
					]
				],
				"mustHitSection": false
			},
			{
				"typeOfSection": 0,
				"lengthInSteps": 16,
				"sectionNotes": [
					[
						144000,
						1,
						230.769230769231
					],
					[
						144307.692307692,
						0,
						0
					],
					[
						144307.692307692,
						3,
						0
					],
					[
						144461.538461539,
						1,
						0
					],
					[
						144615.384615385,
						0,
						0
					],
					[
						144615.384615385,
						2,
						538.461538461538
					],
					[
						144000,
						5,
						230.769230769231
					],
					[
						144307.692307692,
						4,
						0
					],
					[
						144307.692307692,
						7,
						0
					],
					[
						144461.538461539,
						5,
						0
					],
					[
						144615.384615385,
						4,
						0
					],
					[
						144615.384615385,
						6,
						538.461538461538
					]
				],
				"mustHitSection": true
			},
			{
				"typeOfSection": 0,
				"lengthInSteps": 16,
				"sectionNotes": [
					[
						145230.769230769,
						4,
						230.769230769231
					],
					[
						145230.769230769,
						7,
						0
					],
					[
						145538.461538462,
						5,
						0
					],
					[
						145692.307692308,
						6,
						0
					],
					[
						145846.153846154,
						4,
						230.769230769231
					],
					[
						146153.846153846,
						7,
						0
					],
					[
						146307.692307692,
						5,
						0
					],
					[
						145846.153846154,
						7,
						0
					],
					[
						145230.769230769,
						0,
						230.769230769231
					],
					[
						145230.769230769,
						3,
						0
					],
					[
						145538.461538462,
						1,
						0
					],
					[
						145692.307692308,
						2,
						0
					],
					[
						145846.153846154,
						0,
						230.769230769231
					],
					[
						146153.846153846,
						3,
						0
					],
					[
						146307.692307692,
						1,
						0
					],
					[
						145846.153846154,
						3,
						0
					]
				],
				"mustHitSection": false
			},
			{
				"typeOfSection": 0,
				"lengthInSteps": 16,
				"sectionNotes": [
					[
						146461.538461539,
						3,
						384.615384615385
					],
					[
						146923.076923077,
						2,
						384.615384615385
					],
					[
						147384.615384615,
						0,
						230.769230769231
					],
					[
						146923.076923077,
						1,
						384.615384615385
					],
					[
						147384.615384615,
						3,
						230.769230769231
					],
					[
						146461.538461539,
						7,
						384.615384615385
					],
					[
						146923.076923077,
						6,
						384.615384615385
					],
					[
						147384.615384615,
						4,
						230.769230769231
					],
					[
						146923.076923077,
						5,
						384.615384615385
					],
					[
						147384.615384615,
						7,
						230.769230769231
					]
				],
				"mustHitSection": true
			},
			{
				"typeOfSection": 0,
				"lengthInSteps": 16,
				"sectionNotes": [
					[
						147692.307692308,
						4,
						0
					],
					[
						147692.307692308,
						7,
						0
					],
					[
						147846.153846154,
						6,
						0
					],
					[
						148000,
						7,
						230.769230769231
					],
					[
						148307.692307692,
						5,
						0
					],
					[
						148307.692307692,
						4,
						230.769230769231
					],
					[
						148615.384615385,
						6,
						230.769230769231
					],
					[
						147692.307692308,
						0,
						0
					],
					[
						147692.307692308,
						3,
						0
					],
					[
						147846.153846154,
						2,
						0
					],
					[
						148000,
						3,
						230.769230769231
					],
					[
						148307.692307692,
						1,
						0
					],
					[
						148307.692307692,
						0,
						230.769230769231
					],
					[
						148615.384615385,
						2,
						230.769230769231
					]
				],
				"mustHitSection": false
			},
			{
				"typeOfSection": 0,
				"lengthInSteps": 16,
				"sectionNotes": [
					[
						148923.076923077,
						3,
						0
					],
					[
						149076.923076923,
						0,
						0
					],
					[
						149230.769230769,
						2,
						230.769230769231
					],
					[
						149538.461538462,
						3,
						230.769230769231
					],
					[
						149538.461538462,
						0,
						0
					],
					[
						149230.769230769,
						1,
						0
					],
					[
						149846.153846154,
						0,
						0
					],
					[
						150000,
						1,
						0
					],
					[
						148923.076923077,
						7,
						0
					],
					[
						149076.923076923,
						4,
						0
					],
					[
						149230.769230769,
						6,
						230.769230769231
					],
					[
						149538.461538462,
						7,
						230.769230769231
					],
					[
						149538.461538462,
						4,
						0
					],
					[
						149230.769230769,
						5,
						0
					],
					[
						149846.153846154,
						4,
						0
					],
					[
						150000,
						5,
						0
					]
				],
				"mustHitSection": true
			},
			{
				"typeOfSection": 0,
				"lengthInSteps": 16,
				"sectionNotes": [
					[
						150153.846153846,
						6,
						230.769230769231
					],
					[
						150461.538461539,
						4,
						230.769230769231
					],
					[
						150769.230769231,
						5,
						230.769230769231
					],
					[
						150461.538461539,
						7,
						0
					],
					[
						151076.923076923,
						6,
						0
					],
					[
						151230.769230769,
						7,
						0
					],
					[
						150153.846153846,
						2,
						230.769230769231
					],
					[
						150461.538461539,
						0,
						230.769230769231
					],
					[
						150769.230769231,
						1,
						230.769230769231
					],
					[
						150461.538461539,
						3,
						0
					],
					[
						151076.923076923,
						2,
						0
					],
					[
						151230.769230769,
						3,
						0
					]
				],
				"mustHitSection": false
			},
			{
				"typeOfSection": 0,
				"lengthInSteps": 16,
				"sectionNotes": [
					[
						151384.615384615,
						0,
						538.461538461538
					],
					[
						152000,
						2,
						538.461538461538
					],
					[
						152000,
						3,
						0
					],
					[
						151384.615384615,
						4,
						538.461538461538
					],
					[
						152000,
						6,
						538.461538461538
					],
					[
						152000,
						7,
						0
					]
				],
				"mustHitSection": true
			},
			{
				"typeOfSection": 0,
				"lengthInSteps": 16,
				"sectionNotes": [
					[
						153384.615384615,
						6,
						0
					],
					[
						153538.461538462,
						4,
						0
					],
					[
						152923.076923077,
						6,
						0
					],
					[
						152923.076923077,
						7,
						0
					],
					[
						153384.615384615,
						5,
						0
					],
					[
						152615.384615385,
						3,
						230.769230769231
					],
					[
						153076.923076923,
						2,
						0
					],
					[
						153076.923076923,
						1,
						0
					],
					[
						152923.076923077,
						0,
						0
					],
					[
						153230.769230769,
						3,
						0
					],
					[
						153384.615384615,
						1,
						0
					],
					[
						153538.461538462,
						2,
						0
					],
					[
						153692.307692308,
						0,
						0
					]
				],
				"mustHitSection": false
			},
			{
				"typeOfSection": 0,
				"lengthInSteps": 16,
				"sectionNotes": [
					[
						153846.153846154,
						6,
						538.461538461538
					],
					[
						153846.153846154,
						5,
						0
					],
					[
						154461.538461539,
						7,
						538.461538461538
					],
					[
						154461.538461539,
						4,
						0
					],
					[
						153846.153846154,
						2,
						0
					],
					[
						154000,
						1,
						0
					],
					[
						154153.846153846,
						0,
						0
					],
					[
						154307.692307692,
						3,
						0
					],
					[
						154461.538461539,
						0,
						0
					],
					[
						154461.538461539,
						2,
						230.769230769231
					],
					[
						154769.230769231,
						1,
						230.769230769231
					]
				],
				"mustHitSection": false
			},
			{
				"typeOfSection": 0,
				"lengthInSteps": 16,
				"sectionNotes": [
					[
						155076.923076923,
						5,
						0
					],
					[
						155230.769230769,
						6,
						0
					],
					[
						155384.615384615,
						4,
						0
					],
					[
						155692.307692308,
						6,
						0
					],
					[
						155692.307692308,
						7,
						0
					],
					[
						155846.153846154,
						5,
						0
					],
					[
						156000,
						4,
						230.769230769231
					],
					[
						155384.615384615,
						7,
						0
					],
					[
						156000,
						7,
						230.769230769231
					],
					[
						155384.615384615,
						2,
						230.769230769231
					],
					[
						155692.307692308,
						1,
						0
					],
					[
						155692.307692308,
						3,
						0
					],
					[
						155846.153846154,
						0,
						0
					],
					[
						156153.846153846,
						2,
						0
					],
					[
						155076.923076923,
						0,
						0
					],
					[
						155230.769230769,
						3,
						0
					]
				],
				"mustHitSection": false
			},
			{
				"typeOfSection": 0,
				"lengthInSteps": 16,
				"sectionNotes": [
					[
						156307.692307692,
						6,
						538.461538461538
					],
					[
						156923.076923077,
						4,
						0
					],
					[
						156923.076923077,
						5,
						538.461538461538
					],
					[
						156923.076923077,
						2,
						538.461538461538
					],
					[
						156307.692307692,
						1,
						538.461538461538
					],
					[
						156307.692307692,
						0,
						538.461538461538
					],
					[
						156923.076923077,
						3,
						538.461538461538
					]
				],
				"mustHitSection": false
			},
			{
				"typeOfSection": 0,
				"lengthInSteps": 16,
				"sectionNotes": [
					[
						158307.692307692,
						6,
						0
					],
					[
						158461.538461539,
						4,
						0
					],
					[
						157846.153846154,
						6,
						0
					],
					[
						157846.153846154,
						7,
						0
					],
					[
						158307.692307692,
						5,
						0
					],
					[
						157538.461538462,
						3,
						230.769230769231
					],
					[
						158000,
						2,
						0
					],
					[
						158000,
						1,
						0
					],
					[
						157846.153846154,
						0,
						0
					],
					[
						158153.846153846,
						3,
						0
					],
					[
						158307.692307692,
						1,
						0
					],
					[
						158461.538461539,
						2,
						0
					],
					[
						158615.384615385,
						0,
						0
					]
				],
				"mustHitSection": true
			},
			{
				"typeOfSection": 0,
				"lengthInSteps": 16,
				"sectionNotes": [
					[
						158769.230769231,
						6,
						538.461538461538
					],
					[
						158769.230769231,
						5,
						0
					],
					[
						159384.615384615,
						7,
						538.461538461538
					],
					[
						159384.615384615,
						4,
						0
					],
					[
						158769.230769231,
						2,
						0
					],
					[
						158923.076923077,
						1,
						0
					],
					[
						159076.923076923,
						0,
						0
					],
					[
						159230.769230769,
						3,
						0
					],
					[
						159384.615384615,
						0,
						0
					],
					[
						159384.615384615,
						2,
						230.769230769231
					],
					[
						159692.307692308,
						1,
						230.769230769231
					]
				],
				"mustHitSection": true
			},
			{
				"typeOfSection": 0,
				"lengthInSteps": 16,
				"sectionNotes": [
					[
						160000,
						5,
						0
					],
					[
						160153.846153846,
						6,
						0
					],
					[
						160307.692307692,
						4,
						0
					],
					[
						160615.384615385,
						6,
						0
					],
					[
						160615.384615385,
						7,
						0
					],
					[
						160769.230769231,
						5,
						0
					],
					[
						160923.076923077,
						4,
						230.769230769231
					],
					[
						160307.692307692,
						7,
						0
					],
					[
						160923.076923077,
						7,
						230.769230769231
					],
					[
						160307.692307692,
						2,
						230.769230769231
					],
					[
						160615.384615385,
						1,
						0
					],
					[
						160615.384615385,
						3,
						0
					],
					[
						160769.230769231,
						0,
						0
					],
					[
						161076.923076923,
						2,
						0
					],
					[
						160000,
						0,
						0
					],
					[
						160153.846153846,
						3,
						0
					]
				],
				"mustHitSection": true
			},
			{
				"typeOfSection": 0,
				"lengthInSteps": 16,
				"sectionNotes": [
					[
						161230.769230769,
						6,
						538.461538461538
					],
					[
						161846.153846154,
						4,
						0
					],
					[
						161846.153846154,
						5,
						538.461538461538
					],
					[
						161846.153846154,
						2,
						538.461538461538
					],
					[
						161230.769230769,
						1,
						538.461538461538
					],
					[
						161230.769230769,
						0,
						538.461538461538
					],
					[
						161846.153846154,
						3,
						538.461538461538
					]
				],
				"mustHitSection": true
			},
			{
				"sectionBeats": 4,
				"sectionNotes": [
					[
						162461.538461538,
						0,
						1576.92307692308
					],
					[
						162461.538461538,
						1,
						1576.92307692308
					],
					[
						162461.538461538,
						2,
						1576.92307692308
					],
					[
						162461.538461538,
						3,
						1576.92307692308
					],
					[
						162461.538461538,
						4,
						1576.92307692308
					],
					[
						162461.538461538,
						5,
						1576.92307692308
					],
					[
						162461.538461538,
						6,
						1576.92307692308
					],
					[
						162461.538461538,
						7,
						1576.92307692308
					]
				],
				"typeOfSection": 0,
				"gfSection": false,
				"altAnim": false,
				"mustHitSection": false,
				"changeBPM": false,
				"bpm": 195
			},
			{
				"sectionBeats": 4,
				"sectionNotes": [],
				"typeOfSection": 0,
				"gfSection": false,
				"altAnim": false,
				"mustHitSection": false,
				"changeBPM": false,
				"bpm": 195
			},
			{
				"typeOfSection": 0,
				"sectionNotes": [],
				"sectionBeats": 4,
				"altAnim": false,
				"gfSection": false,
				"bpm": 195,
				"changeBPM": false,
				"mustHitSection": true
			},
			{
				"sectionBeats": 4,
				"sectionNotes": [],
				"typeOfSection": 0,
				"gfSection": false,
				"altAnim": false,
				"mustHitSection": true,
				"changeBPM": false,
				"bpm": 195
			},
			{
				"sectionBeats": 4,
				"sectionNotes": [],
				"typeOfSection": 0,
				"gfSection": false,
				"altAnim": false,
				"mustHitSection": true,
				"changeBPM": false,
				"bpm": 195
			},
			{
				"sectionBeats": 4,
				"sectionNotes": [],
				"typeOfSection": 0,
				"gfSection": false,
				"altAnim": false,
				"mustHitSection": true,
				"changeBPM": false,
				"bpm": 195
			},
			{
				"sectionBeats": 4,
				"sectionNotes": [],
				"typeOfSection": 0,
				"gfSection": false,
				"altAnim": false,
				"mustHitSection": true,
				"changeBPM": false,
				"bpm": 195
			},
			{
				"sectionBeats": 4,
				"sectionNotes": [],
				"typeOfSection": 0,
				"gfSection": false,
				"altAnim": false,
				"mustHitSection": true,
				"changeBPM": false,
				"bpm": 195
			},
			{
				"sectionBeats": 4,
				"sectionNotes": [],
				"typeOfSection": 0,
				"gfSection": false,
				"altAnim": false,
				"mustHitSection": true,
				"changeBPM": false,
				"bpm": 195
			},
			{
				"sectionBeats": 4,
				"sectionNotes": [],
				"typeOfSection": 0,
				"gfSection": false,
				"altAnim": false,
				"mustHitSection": true,
				"changeBPM": false,
				"bpm": 195
			},
			{
				"sectionBeats": 4,
				"sectionNotes": [],
				"typeOfSection": 0,
				"gfSection": false,
				"altAnim": false,
				"mustHitSection": true,
				"changeBPM": false,
				"bpm": 195
			},
			{
				"typeOfSection": 0,
				"sectionNotes": [],
				"sectionBeats": 4,
				"altAnim": false,
				"gfSection": false,
				"bpm": 195,
				"changeBPM": false,
				"mustHitSection": true
			},
			{
				"sectionBeats": 4,
				"sectionNotes": [],
				"typeOfSection": 0,
				"gfSection": false,
				"altAnim": false,
				"mustHitSection": true,
				"changeBPM": false,
				"bpm": 195
			},
			{
				"gfSection": false,
				"altAnim": false,
				"typeOfSection": 0,
				"sectionNotes": [],
				"bpm": 195,
				"sectionBeats": 4,
				"changeBPM": false,
				"mustHitSection": true
			}
		],
		"gfVersion": "animator-gf-noteblock",
		"events": [],
		"player3": null,
		"song": "Proficiency",
		"sections": 0,
		"needsVoices": true,
		"validScore": true,
		"stage": "desktop",
		"bpm": 195,
		"speed": 3
	}
}