<?xml version="1.0" encoding="utf-8"?>
<TextureAtlas imagePath="microsoft_sam.png">
	<!-- Created with Adobe Animate version 21.0.9.42677 -->
	<!-- http://www.adobe.com/products/animate.html -->
	<SubTexture name="Samidle0000" x="0" y="0" width="800" height="800"/>
	<SubTexture name="Samidle0001" x="800" y="0" width="800" height="800"/>
	<SubTexture name="Samidle0002" x="1600" y="0" width="800" height="800"/>
	<SubTexture name="Samidle0003" x="2400" y="0" width="800" height="800"/>
	<SubTexture name="Samidle0004" x="3200" y="0" width="800" height="800"/>
	<SubTexture name="Samidle0005" x="4000" y="0" width="800" height="800"/>
	<SubTexture name="Samidle0006" x="4800" y="0" width="800" height="800"/>
	<SubTexture name="Samidle0007" x="5600" y="0" width="800" height="800"/>
	<SubTexture name="Samleft0000" x="6400" y="0" width="800" height="800"/>
	<SubTexture name="Samleft0001" x="7200" y="0" width="800" height="800"/>
	<SubTexture name="Samleft0002" x="0" y="800" width="800" height="800"/>
	<SubTexture name="Samleft0003" x="800" y="800" width="800" height="800"/>
	<SubTexture name="Samleft0004" x="1600" y="800" width="800" height="800"/>
	<SubTexture name="Samdown0000" x="2400" y="800" width="800" height="800"/>
	<SubTexture name="Samdown0001" x="3200" y="800" width="800" height="800"/>
	<SubTexture name="Samdown0002" x="4000" y="800" width="800" height="800"/>
	<SubTexture name="Samdown0003" x="4800" y="800" width="800" height="800"/>
	<SubTexture name="Samdown0004" x="5600" y="800" width="800" height="800"/>
	<SubTexture name="Samup0000" x="6400" y="800" width="800" height="800"/>
	<SubTexture name="Samup0001" x="7200" y="800" width="800" height="800"/>
	<SubTexture name="Samup0002" x="0" y="1600" width="800" height="800"/>
	<SubTexture name="Samup0003" x="800" y="1600" width="800" height="800"/>
	<SubTexture name="Samup0004" x="1600" y="1600" width="800" height="800"/>
	<SubTexture name="Samright0000" x="2400" y="1600" width="800" height="800"/>
	<SubTexture name="Samright0001" x="3200" y="1600" width="800" height="800"/>
	<SubTexture name="Samright0002" x="4000" y="1600" width="800" height="800"/>
	<SubTexture name="Samright0003" x="4800" y="1600" width="800" height="800"/>
	<SubTexture name="Samright0004" x="5600" y="1600" width="800" height="800"/>
</TextureAtlas>
